{
  "type": "File",
  "start": 0,
  "end": 398,
  "loc": {
    "start": {
      "line": 1,
      "column": 0
    },
    "end": {
      "line": 15,
      "column": 0
    }
  },
  "program": {
    "type": "Program",
    "start": 0,
    "end": 398,
    "loc": {
      "start": {
        "line": 1,
        "column": 0
      },
      "end": {
        "line": 15,
        "column": 0
      }
    },
    "sourceType": "module",
    "body": [
      {
        "type": "ImportDeclaration",
        "start": 0,
        "end": 40,
        "loc": {
          "start": {
            "line": 1,
            "column": 0
          },
          "end": {
            "line": 1,
            "column": 40
          }
        },
        "specifiers": [
          {
            "type": "ImportDefaultSpecifier",
            "start": 7,
            "end": 13,
            "loc": {
              "start": {
                "line": 1,
                "column": 7
              },
              "end": {
                "line": 1,
                "column": 13
              }
            },
            "local": {
              "type": "Identifier",
              "start": 7,
              "end": 13,
              "loc": {
                "start": {
                  "line": 1,
                  "column": 7
                },
                "end": {
                  "line": 1,
                  "column": 13
                },
                "identifierName": "curryN"
              },
              "name": "curryN"
            }
          }
        ],
        "source": {
          "type": "StringLiteral",
          "start": 19,
          "end": 39,
          "loc": {
            "start": {
              "line": 1,
              "column": 19
            },
            "end": {
              "line": 1,
              "column": 39
            }
          },
          "extra": {
            "rawValue": "../function/curryN",
            "raw": "'../function/curryN'"
          },
          "value": "../function/curryN"
        },
        "trailingComments": [
          {
            "type": "CommentBlock",
            "value": "*\n * Checks if a string starts with the provided prefix\n *\n * @param {string} prefix\n * @param {string} str\n * @return {Boolean}\n * @example\n *\n *      startsWith('a', 'abc')                //=> true\n *      startsWith('b', 'abc')                //=> false\n ",
            "start": 42,
            "end": 304,
            "loc": {
              "start": {
                "line": 3,
                "column": 0
              },
              "end": {
                "line": 13,
                "column": 3
              }
            }
          }
        ]
      },
      {
        "type": "ExportDefaultDeclaration",
        "start": 305,
        "end": 397,
        "loc": {
          "start": {
            "line": 14,
            "column": 0
          },
          "end": {
            "line": 14,
            "column": 92
          }
        },
        "declaration": {
          "type": "ArrowFunctionExpression",
          "start": 330,
          "end": 395,
          "loc": {
            "start": {
              "line": 14,
              "column": 25
            },
            "end": {
              "line": 14,
              "column": 90
            }
          },
          "id": null,
          "generator": false,
          "expression": true,
          "async": false,
          "params": [
            {
              "type": "AssignmentPattern",
              "start": 331,
              "end": 342,
              "loc": {
                "start": {
                  "line": 14,
                  "column": 26
                },
                "end": {
                  "line": 14,
                  "column": 37
                }
              },
              "left": {
                "type": "Identifier",
                "start": 331,
                "end": 337,
                "loc": {
                  "start": {
                    "line": 14,
                    "column": 26
                  },
                  "end": {
                    "line": 14,
                    "column": 32
                  },
                  "identifierName": "prefix"
                },
                "name": "prefix"
              },
              "right": {
                "type": "StringLiteral",
                "start": 340,
                "end": 342,
                "loc": {
                  "start": {
                    "line": 14,
                    "column": 35
                  },
                  "end": {
                    "line": 14,
                    "column": 37
                  }
                },
                "extra": {
                  "rawValue": "",
                  "raw": "''"
                },
                "value": ""
              }
            },
            {
              "type": "AssignmentPattern",
              "start": 344,
              "end": 352,
              "loc": {
                "start": {
                  "line": 14,
                  "column": 39
                },
                "end": {
                  "line": 14,
                  "column": 47
                }
              },
              "left": {
                "type": "Identifier",
                "start": 344,
                "end": 347,
                "loc": {
                  "start": {
                    "line": 14,
                    "column": 39
                  },
                  "end": {
                    "line": 14,
                    "column": 42
                  },
                  "identifierName": "str"
                },
                "name": "str"
              },
              "right": {
                "type": "StringLiteral",
                "start": 350,
                "end": 352,
                "loc": {
                  "start": {
                    "line": 14,
                    "column": 45
                  },
                  "end": {
                    "line": 14,
                    "column": 47
                  }
                },
                "extra": {
                  "rawValue": "",
                  "raw": "''"
                },
                "value": ""
              }
            }
          ],
          "body": {
            "type": "BinaryExpression",
            "start": 357,
            "end": 395,
            "loc": {
              "start": {
                "line": 14,
                "column": 52
              },
              "end": {
                "line": 14,
                "column": 90
              }
            },
            "left": {
              "type": "CallExpression",
              "start": 357,
              "end": 384,
              "loc": {
                "start": {
                  "line": 14,
                  "column": 52
                },
                "end": {
                  "line": 14,
                  "column": 79
                }
              },
              "callee": {
                "type": "MemberExpression",
                "start": 357,
                "end": 366,
                "loc": {
                  "start": {
                    "line": 14,
                    "column": 52
                  },
                  "end": {
                    "line": 14,
                    "column": 61
                  }
                },
                "object": {
                  "type": "Identifier",
                  "start": 357,
                  "end": 360,
                  "loc": {
                    "start": {
                      "line": 14,
                      "column": 52
                    },
                    "end": {
                      "line": 14,
                      "column": 55
                    },
                    "identifierName": "str"
                  },
                  "name": "str"
                },
                "property": {
                  "type": "Identifier",
                  "start": 361,
                  "end": 366,
                  "loc": {
                    "start": {
                      "line": 14,
                      "column": 56
                    },
                    "end": {
                      "line": 14,
                      "column": 61
                    },
                    "identifierName": "slice"
                  },
                  "name": "slice"
                },
                "computed": false
              },
              "arguments": [
                {
                  "type": "NumericLiteral",
                  "start": 367,
                  "end": 368,
                  "loc": {
                    "start": {
                      "line": 14,
                      "column": 62
                    },
                    "end": {
                      "line": 14,
                      "column": 63
                    }
                  },
                  "extra": {
                    "rawValue": 0,
                    "raw": "0"
                  },
                  "value": 0
                },
                {
                  "type": "MemberExpression",
                  "start": 370,
                  "end": 383,
                  "loc": {
                    "start": {
                      "line": 14,
                      "column": 65
                    },
                    "end": {
                      "line": 14,
                      "column": 78
                    }
                  },
                  "object": {
                    "type": "Identifier",
                    "start": 370,
                    "end": 376,
                    "loc": {
                      "start": {
                        "line": 14,
                        "column": 65
                      },
                      "end": {
                        "line": 14,
                        "column": 71
                      },
                      "identifierName": "prefix"
                    },
                    "name": "prefix"
                  },
                  "property": {
                    "type": "Identifier",
                    "start": 377,
                    "end": 383,
                    "loc": {
                      "start": {
                        "line": 14,
                        "column": 72
                      },
                      "end": {
                        "line": 14,
                        "column": 78
                      },
                      "identifierName": "length"
                    },
                    "name": "length"
                  },
                  "computed": false
                }
              ]
            },
            "operator": "===",
            "right": {
              "type": "Identifier",
              "start": 389,
              "end": 395,
              "loc": {
                "start": {
                  "line": 14,
                  "column": 84
                },
                "end": {
                  "line": 14,
                  "column": 90
                },
                "identifierName": "prefix"
              },
              "name": "prefix"
            }
          },
          "_curryN": 2,
          "leadingComments": [
            {
              "type": "CommentBlock",
              "value": "*\n * Checks if a string starts with the provided prefix\n *\n * @param {string} prefix\n * @param {string} str\n * @return {Boolean}\n * @example\n *\n *      startsWith('a', 'abc')                //=> true\n *      startsWith('b', 'abc')                //=> false\n ",
              "start": 42,
              "end": 304,
              "loc": {
                "start": {
                  "line": 3,
                  "column": 0
                },
                "end": {
                  "line": 13,
                  "column": 3
                }
              }
            }
          ],
          "trailingComments": []
        },
        "leadingComments": [
          {
            "type": "CommentBlock",
            "value": "*\n * Checks if a string starts with the provided prefix\n *\n * @param {string} prefix\n * @param {string} str\n * @return {Boolean}\n * @example\n *\n *      startsWith('a', 'abc')                //=> true\n *      startsWith('b', 'abc')                //=> false\n ",
            "start": 42,
            "end": 304,
            "loc": {
              "start": {
                "line": 3,
                "column": 0
              },
              "end": {
                "line": 13,
                "column": 3
              }
            }
          }
        ]
      }
    ],
    "directives": []
  },
  "comments": [
    {
      "type": "CommentBlock",
      "value": "*\n * Checks if a string starts with the provided prefix\n *\n * @param {string} prefix\n * @param {string} str\n * @return {Boolean}\n * @example\n *\n *      startsWith('a', 'abc')                //=> true\n *      startsWith('b', 'abc')                //=> false\n ",
      "start": 42,
      "end": 304,
      "loc": {
        "start": {
          "line": 3,
          "column": 0
        },
        "end": {
          "line": 13,
          "column": 3
        }
      }
    }
  ],
  "tokens": [
    {
      "type": {
        "label": "import",
        "keyword": "import",
        "beforeExpr": false,
        "startsExpr": true,
        "rightAssociative": false,
        "isLoop": false,
        "isAssign": false,
        "prefix": false,
        "postfix": false,
        "binop": null,
        "updateContext": null
      },
      "value": "import",
      "start": 0,
      "end": 6,
      "loc": {
        "start": {
          "line": 1,
          "column": 0
        },
        "end": {
          "line": 1,
          "column": 6
        }
      }
    },
    {
      "type": {
        "label": "name",
        "beforeExpr": false,
        "startsExpr": true,
        "rightAssociative": false,
        "isLoop": false,
        "isAssign": false,
        "prefix": false,
        "postfix": false,
        "binop": null
      },
      "value": "curryN",
      "start": 7,
      "end": 13,
      "loc": {
        "start": {
          "line": 1,
          "column": 7
        },
        "end": {
          "line": 1,
          "column": 13
        }
      }
    },
    {
      "type": {
        "label": "name",
        "beforeExpr": false,
        "startsExpr": true,
        "rightAssociative": false,
        "isLoop": false,
        "isAssign": false,
        "prefix": false,
        "postfix": false,
        "binop": null
      },
      "value": "from",
      "start": 14,
      "end": 18,
      "loc": {
        "start": {
          "line": 1,
          "column": 14
        },
        "end": {
          "line": 1,
          "column": 18
        }
      }
    },
    {
      "type": {
        "label": "string",
        "beforeExpr": false,
        "startsExpr": true,
        "rightAssociative": false,
        "isLoop": false,
        "isAssign": false,
        "prefix": false,
        "postfix": false,
        "binop": null,
        "updateContext": null
      },
      "value": "../function/curryN",
      "start": 19,
      "end": 39,
      "loc": {
        "start": {
          "line": 1,
          "column": 19
        },
        "end": {
          "line": 1,
          "column": 39
        }
      }
    },
    {
      "type": {
        "label": ";",
        "beforeExpr": true,
        "startsExpr": false,
        "rightAssociative": false,
        "isLoop": false,
        "isAssign": false,
        "prefix": false,
        "postfix": false,
        "binop": null,
        "updateContext": null
      },
      "start": 39,
      "end": 40,
      "loc": {
        "start": {
          "line": 1,
          "column": 39
        },
        "end": {
          "line": 1,
          "column": 40
        }
      }
    },
    {
      "type": "CommentBlock",
      "value": "*\n * Checks if a string starts with the provided prefix\n *\n * @param {string} prefix\n * @param {string} str\n * @return {Boolean}\n * @example\n *\n *      startsWith('a', 'abc')                //=> true\n *      startsWith('b', 'abc')                //=> false\n ",
      "start": 42,
      "end": 304,
      "loc": {
        "start": {
          "line": 3,
          "column": 0
        },
        "end": {
          "line": 13,
          "column": 3
        }
      }
    },
    {
      "type": {
        "label": "export",
        "keyword": "export",
        "beforeExpr": false,
        "startsExpr": false,
        "rightAssociative": false,
        "isLoop": false,
        "isAssign": false,
        "prefix": false,
        "postfix": false,
        "binop": null,
        "updateContext": null
      },
      "value": "export",
      "start": 305,
      "end": 311,
      "loc": {
        "start": {
          "line": 14,
          "column": 0
        },
        "end": {
          "line": 14,
          "column": 6
        }
      }
    },
    {
      "type": {
        "label": "default",
        "keyword": "default",
        "beforeExpr": true,
        "startsExpr": false,
        "rightAssociative": false,
        "isLoop": false,
        "isAssign": false,
        "prefix": false,
        "postfix": false,
        "binop": null,
        "updateContext": null
      },
      "value": "default",
      "start": 312,
      "end": 319,
      "loc": {
        "start": {
          "line": 14,
          "column": 7
        },
        "end": {
          "line": 14,
          "column": 14
        }
      }
    },
    {
      "type": {
        "label": "name",
        "beforeExpr": false,
        "startsExpr": true,
        "rightAssociative": false,
        "isLoop": false,
        "isAssign": false,
        "prefix": false,
        "postfix": false,
        "binop": null
      },
      "value": "curryN",
      "start": 320,
      "end": 326,
      "loc": {
        "start": {
          "line": 14,
          "column": 15
        },
        "end": {
          "line": 14,
          "column": 21
        }
      }
    },
    {
      "type": {
        "label": "(",
        "beforeExpr": true,
        "startsExpr": true,
        "rightAssociative": false,
        "isLoop": false,
        "isAssign": false,
        "prefix": false,
        "postfix": false,
        "binop": null
      },
      "start": 326,
      "end": 327,
      "loc": {
        "start": {
          "line": 14,
          "column": 21
        },
        "end": {
          "line": 14,
          "column": 22
        }
      }
    },
    {
      "type": {
        "label": "num",
        "beforeExpr": false,
        "startsExpr": true,
        "rightAssociative": false,
        "isLoop": false,
        "isAssign": false,
        "prefix": false,
        "postfix": false,
        "binop": null,
        "updateContext": null
      },
      "value": 2,
      "start": 327,
      "end": 328,
      "loc": {
        "start": {
          "line": 14,
          "column": 22
        },
        "end": {
          "line": 14,
          "column": 23
        }
      }
    },
    {
      "type": {
        "label": ",",
        "beforeExpr": true,
        "startsExpr": false,
        "rightAssociative": false,
        "isLoop": false,
        "isAssign": false,
        "prefix": false,
        "postfix": false,
        "binop": null,
        "updateContext": null
      },
      "start": 328,
      "end": 329,
      "loc": {
        "start": {
          "line": 14,
          "column": 23
        },
        "end": {
          "line": 14,
          "column": 24
        }
      }
    },
    {
      "type": {
        "label": "(",
        "beforeExpr": true,
        "startsExpr": true,
        "rightAssociative": false,
        "isLoop": false,
        "isAssign": false,
        "prefix": false,
        "postfix": false,
        "binop": null
      },
      "start": 330,
      "end": 331,
      "loc": {
        "start": {
          "line": 14,
          "column": 25
        },
        "end": {
          "line": 14,
          "column": 26
        }
      }
    },
    {
      "type": {
        "label": "name",
        "beforeExpr": false,
        "startsExpr": true,
        "rightAssociative": false,
        "isLoop": false,
        "isAssign": false,
        "prefix": false,
        "postfix": false,
        "binop": null
      },
      "value": "prefix",
      "start": 331,
      "end": 337,
      "loc": {
        "start": {
          "line": 14,
          "column": 26
        },
        "end": {
          "line": 14,
          "column": 32
        }
      }
    },
    {
      "type": {
        "label": "=",
        "beforeExpr": true,
        "startsExpr": false,
        "rightAssociative": false,
        "isLoop": false,
        "isAssign": true,
        "prefix": false,
        "postfix": false,
        "binop": null,
        "updateContext": null
      },
      "value": "=",
      "start": 338,
      "end": 339,
      "loc": {
        "start": {
          "line": 14,
          "column": 33
        },
        "end": {
          "line": 14,
          "column": 34
        }
      }
    },
    {
      "type": {
        "label": "string",
        "beforeExpr": false,
        "startsExpr": true,
        "rightAssociative": false,
        "isLoop": false,
        "isAssign": false,
        "prefix": false,
        "postfix": false,
        "binop": null,
        "updateContext": null
      },
      "value": "",
      "start": 340,
      "end": 342,
      "loc": {
        "start": {
          "line": 14,
          "column": 35
        },
        "end": {
          "line": 14,
          "column": 37
        }
      }
    },
    {
      "type": {
        "label": ",",
        "beforeExpr": true,
        "startsExpr": false,
        "rightAssociative": false,
        "isLoop": false,
        "isAssign": false,
        "prefix": false,
        "postfix": false,
        "binop": null,
        "updateContext": null
      },
      "start": 342,
      "end": 343,
      "loc": {
        "start": {
          "line": 14,
          "column": 37
        },
        "end": {
          "line": 14,
          "column": 38
        }
      }
    },
    {
      "type": {
        "label": "name",
        "beforeExpr": false,
        "startsExpr": true,
        "rightAssociative": false,
        "isLoop": false,
        "isAssign": false,
        "prefix": false,
        "postfix": false,
        "binop": null
      },
      "value": "str",
      "start": 344,
      "end": 347,
      "loc": {
        "start": {
          "line": 14,
          "column": 39
        },
        "end": {
          "line": 14,
          "column": 42
        }
      }
    },
    {
      "type": {
        "label": "=",
        "beforeExpr": true,
        "startsExpr": false,
        "rightAssociative": false,
        "isLoop": false,
        "isAssign": true,
        "prefix": false,
        "postfix": false,
        "binop": null,
        "updateContext": null
      },
      "value": "=",
      "start": 348,
      "end": 349,
      "loc": {
        "start": {
          "line": 14,
          "column": 43
        },
        "end": {
          "line": 14,
          "column": 44
        }
      }
    },
    {
      "type": {
        "label": "string",
        "beforeExpr": false,
        "startsExpr": true,
        "rightAssociative": false,
        "isLoop": false,
        "isAssign": false,
        "prefix": false,
        "postfix": false,
        "binop": null,
        "updateContext": null
      },
      "value": "",
      "start": 350,
      "end": 352,
      "loc": {
        "start": {
          "line": 14,
          "column": 45
        },
        "end": {
          "line": 14,
          "column": 47
        }
      }
    },
    {
      "type": {
        "label": ")",
        "beforeExpr": false,
        "startsExpr": false,
        "rightAssociative": false,
        "isLoop": false,
        "isAssign": false,
        "prefix": false,
        "postfix": false,
        "binop": null
      },
      "start": 352,
      "end": 353,
      "loc": {
        "start": {
          "line": 14,
          "column": 47
        },
        "end": {
          "line": 14,
          "column": 48
        }
      }
    },
    {
      "type": {
        "label": "=>",
        "beforeExpr": true,
        "startsExpr": false,
        "rightAssociative": false,
        "isLoop": false,
        "isAssign": false,
        "prefix": false,
        "postfix": false,
        "binop": null,
        "updateContext": null
      },
      "start": 354,
      "end": 356,
      "loc": {
        "start": {
          "line": 14,
          "column": 49
        },
        "end": {
          "line": 14,
          "column": 51
        }
      }
    },
    {
      "type": {
        "label": "name",
        "beforeExpr": false,
        "startsExpr": true,
        "rightAssociative": false,
        "isLoop": false,
        "isAssign": false,
        "prefix": false,
        "postfix": false,
        "binop": null
      },
      "value": "str",
      "start": 357,
      "end": 360,
      "loc": {
        "start": {
          "line": 14,
          "column": 52
        },
        "end": {
          "line": 14,
          "column": 55
        }
      }
    },
    {
      "type": {
        "label": ".",
        "beforeExpr": false,
        "startsExpr": false,
        "rightAssociative": false,
        "isLoop": false,
        "isAssign": false,
        "prefix": false,
        "postfix": false,
        "binop": null,
        "updateContext": null
      },
      "start": 360,
      "end": 361,
      "loc": {
        "start": {
          "line": 14,
          "column": 55
        },
        "end": {
          "line": 14,
          "column": 56
        }
      }
    },
    {
      "type": {
        "label": "name",
        "beforeExpr": false,
        "startsExpr": true,
        "rightAssociative": false,
        "isLoop": false,
        "isAssign": false,
        "prefix": false,
        "postfix": false,
        "binop": null
      },
      "value": "slice",
      "start": 361,
      "end": 366,
      "loc": {
        "start": {
          "line": 14,
          "column": 56
        },
        "end": {
          "line": 14,
          "column": 61
        }
      }
    },
    {
      "type": {
        "label": "(",
        "beforeExpr": true,
        "startsExpr": true,
        "rightAssociative": false,
        "isLoop": false,
        "isAssign": false,
        "prefix": false,
        "postfix": false,
        "binop": null
      },
      "start": 366,
      "end": 367,
      "loc": {
        "start": {
          "line": 14,
          "column": 61
        },
        "end": {
          "line": 14,
          "column": 62
        }
      }
    },
    {
      "type": {
        "label": "num",
        "beforeExpr": false,
        "startsExpr": true,
        "rightAssociative": false,
        "isLoop": false,
        "isAssign": false,
        "prefix": false,
        "postfix": false,
        "binop": null,
        "updateContext": null
      },
      "value": 0,
      "start": 367,
      "end": 368,
      "loc": {
        "start": {
          "line": 14,
          "column": 62
        },
        "end": {
          "line": 14,
          "column": 63
        }
      }
    },
    {
      "type": {
        "label": ",",
        "beforeExpr": true,
        "startsExpr": false,
        "rightAssociative": false,
        "isLoop": false,
        "isAssign": false,
        "prefix": false,
        "postfix": false,
        "binop": null,
        "updateContext": null
      },
      "start": 368,
      "end": 369,
      "loc": {
        "start": {
          "line": 14,
          "column": 63
        },
        "end": {
          "line": 14,
          "column": 64
        }
      }
    },
    {
      "type": {
        "label": "name",
        "beforeExpr": false,
        "startsExpr": true,
        "rightAssociative": false,
        "isLoop": false,
        "isAssign": false,
        "prefix": false,
        "postfix": false,
        "binop": null
      },
      "value": "prefix",
      "start": 370,
      "end": 376,
      "loc": {
        "start": {
          "line": 14,
          "column": 65
        },
        "end": {
          "line": 14,
          "column": 71
        }
      }
    },
    {
      "type": {
        "label": ".",
        "beforeExpr": false,
        "startsExpr": false,
        "rightAssociative": false,
        "isLoop": false,
        "isAssign": false,
        "prefix": false,
        "postfix": false,
        "binop": null,
        "updateContext": null
      },
      "start": 376,
      "end": 377,
      "loc": {
        "start": {
          "line": 14,
          "column": 71
        },
        "end": {
          "line": 14,
          "column": 72
        }
      }
    },
    {
      "type": {
        "label": "name",
        "beforeExpr": false,
        "startsExpr": true,
        "rightAssociative": false,
        "isLoop": false,
        "isAssign": false,
        "prefix": false,
        "postfix": false,
        "binop": null
      },
      "value": "length",
      "start": 377,
      "end": 383,
      "loc": {
        "start": {
          "line": 14,
          "column": 72
        },
        "end": {
          "line": 14,
          "column": 78
        }
      }
    },
    {
      "type": {
        "label": ")",
        "beforeExpr": false,
        "startsExpr": false,
        "rightAssociative": false,
        "isLoop": false,
        "isAssign": false,
        "prefix": false,
        "postfix": false,
        "binop": null
      },
      "start": 383,
      "end": 384,
      "loc": {
        "start": {
          "line": 14,
          "column": 78
        },
        "end": {
          "line": 14,
          "column": 79
        }
      }
    },
    {
      "type": {
        "label": "==/!=",
        "beforeExpr": true,
        "startsExpr": false,
        "rightAssociative": false,
        "isLoop": false,
        "isAssign": false,
        "prefix": false,
        "postfix": false,
        "binop": 6,
        "updateContext": null
      },
      "value": "===",
      "start": 385,
      "end": 388,
      "loc": {
        "start": {
          "line": 14,
          "column": 80
        },
        "end": {
          "line": 14,
          "column": 83
        }
      }
    },
    {
      "type": {
        "label": "name",
        "beforeExpr": false,
        "startsExpr": true,
        "rightAssociative": false,
        "isLoop": false,
        "isAssign": false,
        "prefix": false,
        "postfix": false,
        "binop": null
      },
      "value": "prefix",
      "start": 389,
      "end": 395,
      "loc": {
        "start": {
          "line": 14,
          "column": 84
        },
        "end": {
          "line": 14,
          "column": 90
        }
      }
    },
    {
      "type": {
        "label": ")",
        "beforeExpr": false,
        "startsExpr": false,
        "rightAssociative": false,
        "isLoop": false,
        "isAssign": false,
        "prefix": false,
        "postfix": false,
        "binop": null
      },
      "start": 395,
      "end": 396,
      "loc": {
        "start": {
          "line": 14,
          "column": 90
        },
        "end": {
          "line": 14,
          "column": 91
        }
      }
    },
    {
      "type": {
        "label": ";",
        "beforeExpr": true,
        "startsExpr": false,
        "rightAssociative": false,
        "isLoop": false,
        "isAssign": false,
        "prefix": false,
        "postfix": false,
        "binop": null,
        "updateContext": null
      },
      "start": 396,
      "end": 397,
      "loc": {
        "start": {
          "line": 14,
          "column": 91
        },
        "end": {
          "line": 14,
          "column": 92
        }
      }
    },
    {
      "type": {
        "label": "eof",
        "beforeExpr": false,
        "startsExpr": false,
        "rightAssociative": false,
        "isLoop": false,
        "isAssign": false,
        "prefix": false,
        "postfix": false,
        "binop": null,
        "updateContext": null
      },
      "start": 398,
      "end": 398,
      "loc": {
        "start": {
          "line": 15,
          "column": 0
        },
        "end": {
          "line": 15,
          "column": 0
        }
      }
    }
  ]
}