{
  "type": "File",
  "start": 0,
  "end": 799,
  "loc": {
    "start": {
      "line": 1,
      "column": 0
    },
    "end": {
      "line": 27,
      "column": 0
    }
  },
  "program": {
    "type": "Program",
    "start": 0,
    "end": 799,
    "loc": {
      "start": {
        "line": 1,
        "column": 0
      },
      "end": {
        "line": 27,
        "column": 0
      }
    },
    "sourceType": "module",
    "body": [
      {
        "type": "ImportDeclaration",
        "start": 0,
        "end": 30,
        "loc": {
          "start": {
            "line": 1,
            "column": 0
          },
          "end": {
            "line": 1,
            "column": 30
          }
        },
        "specifiers": [
          {
            "type": "ImportDefaultSpecifier",
            "start": 7,
            "end": 13,
            "loc": {
              "start": {
                "line": 1,
                "column": 7
              },
              "end": {
                "line": 1,
                "column": 13
              }
            },
            "local": {
              "type": "Identifier",
              "start": 7,
              "end": 13,
              "loc": {
                "start": {
                  "line": 1,
                  "column": 7
                },
                "end": {
                  "line": 1,
                  "column": 13
                },
                "identifierName": "curryN"
              },
              "name": "curryN"
            }
          }
        ],
        "source": {
          "type": "StringLiteral",
          "start": 19,
          "end": 29,
          "loc": {
            "start": {
              "line": 1,
              "column": 19
            },
            "end": {
              "line": 1,
              "column": 29
            }
          },
          "extra": {
            "rawValue": "./curryN",
            "raw": "'./curryN'"
          },
          "value": "./curryN"
        },
        "trailingComments": [
          {
            "type": "CommentBlock",
            "value": "*\n * Takes a list of predicates and returns a predicate that returns true for a\n * given list of arguments if every one of the provided predicates is satisfied\n * by those arguments.\n *\n * @param {Array} fns predicates\n * @param {...*} args passed arguments to predicates\n * @return {Function}\n * @example\n *\n *      var isQueen = propEq('rank', 'Q');\n *      var isSpade = propEq('suit', '♠︎');\n *      var isQueenOfSpades = allPass([isQueen, isSpade]);\n *\n *      isQueenOfSpades({rank: 'Q', suit: '♣︎'}); //=> false\n *      isQueenOfSpades({rank: 'Q', suit: '♠︎'}); //=> true\n ",
            "start": 31,
            "end": 615,
            "loc": {
              "start": {
                "line": 2,
                "column": 0
              },
              "end": {
                "line": 18,
                "column": 3
              }
            }
          }
        ]
      },
      {
        "type": "ExportDefaultDeclaration",
        "start": 616,
        "end": 798,
        "loc": {
          "start": {
            "line": 19,
            "column": 0
          },
          "end": {
            "line": 26,
            "column": 3
          }
        },
        "declaration": {
          "type": "ArrowFunctionExpression",
          "start": 641,
          "end": 796,
          "loc": {
            "start": {
              "line": 19,
              "column": 25
            },
            "end": {
              "line": 26,
              "column": 1
            }
          },
          "id": null,
          "generator": false,
          "expression": false,
          "async": false,
          "params": [
            {
              "type": "Identifier",
              "start": 642,
              "end": 645,
              "loc": {
                "start": {
                  "line": 19,
                  "column": 26
                },
                "end": {
                  "line": 19,
                  "column": 29
                },
                "identifierName": "fns"
              },
              "name": "fns"
            },
            {
              "type": "RestElement",
              "start": 647,
              "end": 654,
              "loc": {
                "start": {
                  "line": 19,
                  "column": 31
                },
                "end": {
                  "line": 19,
                  "column": 38
                }
              },
              "argument": {
                "type": "Identifier",
                "start": 650,
                "end": 654,
                "loc": {
                  "start": {
                    "line": 19,
                    "column": 34
                  },
                  "end": {
                    "line": 19,
                    "column": 38
                  },
                  "identifierName": "args"
                },
                "name": "args"
              }
            }
          ],
          "body": {
            "type": "BlockStatement",
            "start": 659,
            "end": 796,
            "loc": {
              "start": {
                "line": 19,
                "column": 43
              },
              "end": {
                "line": 26,
                "column": 1
              }
            },
            "body": [
              {
                "type": "ForStatement",
                "start": 665,
                "end": 777,
                "loc": {
                  "start": {
                    "line": 20,
                    "column": 4
                  },
                  "end": {
                    "line": 24,
                    "column": 5
                  }
                },
                "init": {
                  "type": "VariableDeclaration",
                  "start": 670,
                  "end": 679,
                  "loc": {
                    "start": {
                      "line": 20,
                      "column": 9
                    },
                    "end": {
                      "line": 20,
                      "column": 18
                    }
                  },
                  "declarations": [
                    {
                      "type": "VariableDeclarator",
                      "start": 674,
                      "end": 679,
                      "loc": {
                        "start": {
                          "line": 20,
                          "column": 13
                        },
                        "end": {
                          "line": 20,
                          "column": 18
                        }
                      },
                      "id": {
                        "type": "Identifier",
                        "start": 674,
                        "end": 675,
                        "loc": {
                          "start": {
                            "line": 20,
                            "column": 13
                          },
                          "end": {
                            "line": 20,
                            "column": 14
                          },
                          "identifierName": "i"
                        },
                        "name": "i"
                      },
                      "init": {
                        "type": "NumericLiteral",
                        "start": 678,
                        "end": 679,
                        "loc": {
                          "start": {
                            "line": 20,
                            "column": 17
                          },
                          "end": {
                            "line": 20,
                            "column": 18
                          }
                        },
                        "extra": {
                          "rawValue": 0,
                          "raw": "0"
                        },
                        "value": 0
                      }
                    }
                  ],
                  "kind": "let"
                },
                "test": {
                  "type": "BinaryExpression",
                  "start": 681,
                  "end": 695,
                  "loc": {
                    "start": {
                      "line": 20,
                      "column": 20
                    },
                    "end": {
                      "line": 20,
                      "column": 34
                    }
                  },
                  "left": {
                    "type": "Identifier",
                    "start": 681,
                    "end": 682,
                    "loc": {
                      "start": {
                        "line": 20,
                        "column": 20
                      },
                      "end": {
                        "line": 20,
                        "column": 21
                      },
                      "identifierName": "i"
                    },
                    "name": "i"
                  },
                  "operator": "<",
                  "right": {
                    "type": "MemberExpression",
                    "start": 685,
                    "end": 695,
                    "loc": {
                      "start": {
                        "line": 20,
                        "column": 24
                      },
                      "end": {
                        "line": 20,
                        "column": 34
                      }
                    },
                    "object": {
                      "type": "Identifier",
                      "start": 685,
                      "end": 688,
                      "loc": {
                        "start": {
                          "line": 20,
                          "column": 24
                        },
                        "end": {
                          "line": 20,
                          "column": 27
                        },
                        "identifierName": "fns"
                      },
                      "name": "fns"
                    },
                    "property": {
                      "type": "Identifier",
                      "start": 689,
                      "end": 695,
                      "loc": {
                        "start": {
                          "line": 20,
                          "column": 28
                        },
                        "end": {
                          "line": 20,
                          "column": 34
                        },
                        "identifierName": "length"
                      },
                      "name": "length"
                    },
                    "computed": false
                  }
                },
                "update": {
                  "type": "UpdateExpression",
                  "start": 697,
                  "end": 700,
                  "loc": {
                    "start": {
                      "line": 20,
                      "column": 36
                    },
                    "end": {
                      "line": 20,
                      "column": 39
                    }
                  },
                  "operator": "++",
                  "prefix": false,
                  "argument": {
                    "type": "Identifier",
                    "start": 697,
                    "end": 698,
                    "loc": {
                      "start": {
                        "line": 20,
                        "column": 36
                      },
                      "end": {
                        "line": 20,
                        "column": 37
                      },
                      "identifierName": "i"
                    },
                    "name": "i"
                  }
                },
                "body": {
                  "type": "BlockStatement",
                  "start": 702,
                  "end": 777,
                  "loc": {
                    "start": {
                      "line": 20,
                      "column": 41
                    },
                    "end": {
                      "line": 24,
                      "column": 5
                    }
                  },
                  "body": [
                    {
                      "type": "IfStatement",
                      "start": 712,
                      "end": 771,
                      "loc": {
                        "start": {
                          "line": 21,
                          "column": 8
                        },
                        "end": {
                          "line": 23,
                          "column": 9
                        }
                      },
                      "test": {
                        "type": "UnaryExpression",
                        "start": 716,
                        "end": 732,
                        "loc": {
                          "start": {
                            "line": 21,
                            "column": 12
                          },
                          "end": {
                            "line": 21,
                            "column": 28
                          }
                        },
                        "operator": "!",
                        "prefix": true,
                        "argument": {
                          "type": "CallExpression",
                          "start": 717,
                          "end": 732,
                          "loc": {
                            "start": {
                              "line": 21,
                              "column": 13
                            },
                            "end": {
                              "line": 21,
                              "column": 28
                            }
                          },
                          "callee": {
                            "type": "MemberExpression",
                            "start": 717,
                            "end": 723,
                            "loc": {
                              "start": {
                                "line": 21,
                                "column": 13
                              },
                              "end": {
                                "line": 21,
                                "column": 19
                              }
                            },
                            "object": {
                              "type": "Identifier",
                              "start": 717,
                              "end": 720,
                              "loc": {
                                "start": {
                                  "line": 21,
                                  "column": 13
                                },
                                "end": {
                                  "line": 21,
                                  "column": 16
                                },
                                "identifierName": "fns"
                              },
                              "name": "fns"
                            },
                            "property": {
                              "type": "Identifier",
                              "start": 721,
                              "end": 722,
                              "loc": {
                                "start": {
                                  "line": 21,
                                  "column": 17
                                },
                                "end": {
                                  "line": 21,
                                  "column": 18
                                },
                                "identifierName": "i"
                              },
                              "name": "i"
                            },
                            "computed": true
                          },
                          "arguments": [
                            {
                              "type": "SpreadElement",
                              "start": 724,
                              "end": 731,
                              "loc": {
                                "start": {
                                  "line": 21,
                                  "column": 20
                                },
                                "end": {
                                  "line": 21,
                                  "column": 27
                                }
                              },
                              "argument": {
                                "type": "Identifier",
                                "start": 727,
                                "end": 731,
                                "loc": {
                                  "start": {
                                    "line": 21,
                                    "column": 23
                                  },
                                  "end": {
                                    "line": 21,
                                    "column": 27
                                  },
                                  "identifierName": "args"
                                },
                                "name": "args"
                              }
                            }
                          ]
                        },
                        "extra": {
                          "parenthesizedArgument": false
                        }
                      },
                      "consequent": {
                        "type": "BlockStatement",
                        "start": 734,
                        "end": 771,
                        "loc": {
                          "start": {
                            "line": 21,
                            "column": 30
                          },
                          "end": {
                            "line": 23,
                            "column": 9
                          }
                        },
                        "body": [
                          {
                            "type": "ReturnStatement",
                            "start": 748,
                            "end": 761,
                            "loc": {
                              "start": {
                                "line": 22,
                                "column": 12
                              },
                              "end": {
                                "line": 22,
                                "column": 25
                              }
                            },
                            "argument": {
                              "type": "BooleanLiteral",
                              "start": 755,
                              "end": 760,
                              "loc": {
                                "start": {
                                  "line": 22,
                                  "column": 19
                                },
                                "end": {
                                  "line": 22,
                                  "column": 24
                                }
                              },
                              "value": false
                            }
                          }
                        ],
                        "directives": []
                      },
                      "alternate": null
                    }
                  ],
                  "directives": []
                }
              },
              {
                "type": "ReturnStatement",
                "start": 782,
                "end": 794,
                "loc": {
                  "start": {
                    "line": 25,
                    "column": 4
                  },
                  "end": {
                    "line": 25,
                    "column": 16
                  }
                },
                "argument": {
                  "type": "BooleanLiteral",
                  "start": 789,
                  "end": 793,
                  "loc": {
                    "start": {
                      "line": 25,
                      "column": 11
                    },
                    "end": {
                      "line": 25,
                      "column": 15
                    }
                  },
                  "value": true
                }
              }
            ],
            "directives": []
          },
          "_curryN": 2,
          "leadingComments": [
            {
              "type": "CommentBlock",
              "value": "*\n * Takes a list of predicates and returns a predicate that returns true for a\n * given list of arguments if every one of the provided predicates is satisfied\n * by those arguments.\n *\n * @param {Array} fns predicates\n * @param {...*} args passed arguments to predicates\n * @return {Function}\n * @example\n *\n *      var isQueen = propEq('rank', 'Q');\n *      var isSpade = propEq('suit', '♠︎');\n *      var isQueenOfSpades = allPass([isQueen, isSpade]);\n *\n *      isQueenOfSpades({rank: 'Q', suit: '♣︎'}); //=> false\n *      isQueenOfSpades({rank: 'Q', suit: '♠︎'}); //=> true\n ",
              "start": 31,
              "end": 615,
              "loc": {
                "start": {
                  "line": 2,
                  "column": 0
                },
                "end": {
                  "line": 18,
                  "column": 3
                }
              }
            }
          ],
          "trailingComments": []
        },
        "leadingComments": [
          {
            "type": "CommentBlock",
            "value": "*\n * Takes a list of predicates and returns a predicate that returns true for a\n * given list of arguments if every one of the provided predicates is satisfied\n * by those arguments.\n *\n * @param {Array} fns predicates\n * @param {...*} args passed arguments to predicates\n * @return {Function}\n * @example\n *\n *      var isQueen = propEq('rank', 'Q');\n *      var isSpade = propEq('suit', '♠︎');\n *      var isQueenOfSpades = allPass([isQueen, isSpade]);\n *\n *      isQueenOfSpades({rank: 'Q', suit: '♣︎'}); //=> false\n *      isQueenOfSpades({rank: 'Q', suit: '♠︎'}); //=> true\n ",
            "start": 31,
            "end": 615,
            "loc": {
              "start": {
                "line": 2,
                "column": 0
              },
              "end": {
                "line": 18,
                "column": 3
              }
            }
          }
        ]
      }
    ],
    "directives": []
  },
  "comments": [
    {
      "type": "CommentBlock",
      "value": "*\n * Takes a list of predicates and returns a predicate that returns true for a\n * given list of arguments if every one of the provided predicates is satisfied\n * by those arguments.\n *\n * @param {Array} fns predicates\n * @param {...*} args passed arguments to predicates\n * @return {Function}\n * @example\n *\n *      var isQueen = propEq('rank', 'Q');\n *      var isSpade = propEq('suit', '♠︎');\n *      var isQueenOfSpades = allPass([isQueen, isSpade]);\n *\n *      isQueenOfSpades({rank: 'Q', suit: '♣︎'}); //=> false\n *      isQueenOfSpades({rank: 'Q', suit: '♠︎'}); //=> true\n ",
      "start": 31,
      "end": 615,
      "loc": {
        "start": {
          "line": 2,
          "column": 0
        },
        "end": {
          "line": 18,
          "column": 3
        }
      }
    }
  ],
  "tokens": [
    {
      "type": {
        "label": "import",
        "keyword": "import",
        "beforeExpr": false,
        "startsExpr": true,
        "rightAssociative": false,
        "isLoop": false,
        "isAssign": false,
        "prefix": false,
        "postfix": false,
        "binop": null,
        "updateContext": null
      },
      "value": "import",
      "start": 0,
      "end": 6,
      "loc": {
        "start": {
          "line": 1,
          "column": 0
        },
        "end": {
          "line": 1,
          "column": 6
        }
      }
    },
    {
      "type": {
        "label": "name",
        "beforeExpr": false,
        "startsExpr": true,
        "rightAssociative": false,
        "isLoop": false,
        "isAssign": false,
        "prefix": false,
        "postfix": false,
        "binop": null
      },
      "value": "curryN",
      "start": 7,
      "end": 13,
      "loc": {
        "start": {
          "line": 1,
          "column": 7
        },
        "end": {
          "line": 1,
          "column": 13
        }
      }
    },
    {
      "type": {
        "label": "name",
        "beforeExpr": false,
        "startsExpr": true,
        "rightAssociative": false,
        "isLoop": false,
        "isAssign": false,
        "prefix": false,
        "postfix": false,
        "binop": null
      },
      "value": "from",
      "start": 14,
      "end": 18,
      "loc": {
        "start": {
          "line": 1,
          "column": 14
        },
        "end": {
          "line": 1,
          "column": 18
        }
      }
    },
    {
      "type": {
        "label": "string",
        "beforeExpr": false,
        "startsExpr": true,
        "rightAssociative": false,
        "isLoop": false,
        "isAssign": false,
        "prefix": false,
        "postfix": false,
        "binop": null,
        "updateContext": null
      },
      "value": "./curryN",
      "start": 19,
      "end": 29,
      "loc": {
        "start": {
          "line": 1,
          "column": 19
        },
        "end": {
          "line": 1,
          "column": 29
        }
      }
    },
    {
      "type": {
        "label": ";",
        "beforeExpr": true,
        "startsExpr": false,
        "rightAssociative": false,
        "isLoop": false,
        "isAssign": false,
        "prefix": false,
        "postfix": false,
        "binop": null,
        "updateContext": null
      },
      "start": 29,
      "end": 30,
      "loc": {
        "start": {
          "line": 1,
          "column": 29
        },
        "end": {
          "line": 1,
          "column": 30
        }
      }
    },
    {
      "type": "CommentBlock",
      "value": "*\n * Takes a list of predicates and returns a predicate that returns true for a\n * given list of arguments if every one of the provided predicates is satisfied\n * by those arguments.\n *\n * @param {Array} fns predicates\n * @param {...*} args passed arguments to predicates\n * @return {Function}\n * @example\n *\n *      var isQueen = propEq('rank', 'Q');\n *      var isSpade = propEq('suit', '♠︎');\n *      var isQueenOfSpades = allPass([isQueen, isSpade]);\n *\n *      isQueenOfSpades({rank: 'Q', suit: '♣︎'}); //=> false\n *      isQueenOfSpades({rank: 'Q', suit: '♠︎'}); //=> true\n ",
      "start": 31,
      "end": 615,
      "loc": {
        "start": {
          "line": 2,
          "column": 0
        },
        "end": {
          "line": 18,
          "column": 3
        }
      }
    },
    {
      "type": {
        "label": "export",
        "keyword": "export",
        "beforeExpr": false,
        "startsExpr": false,
        "rightAssociative": false,
        "isLoop": false,
        "isAssign": false,
        "prefix": false,
        "postfix": false,
        "binop": null,
        "updateContext": null
      },
      "value": "export",
      "start": 616,
      "end": 622,
      "loc": {
        "start": {
          "line": 19,
          "column": 0
        },
        "end": {
          "line": 19,
          "column": 6
        }
      }
    },
    {
      "type": {
        "label": "default",
        "keyword": "default",
        "beforeExpr": true,
        "startsExpr": false,
        "rightAssociative": false,
        "isLoop": false,
        "isAssign": false,
        "prefix": false,
        "postfix": false,
        "binop": null,
        "updateContext": null
      },
      "value": "default",
      "start": 623,
      "end": 630,
      "loc": {
        "start": {
          "line": 19,
          "column": 7
        },
        "end": {
          "line": 19,
          "column": 14
        }
      }
    },
    {
      "type": {
        "label": "name",
        "beforeExpr": false,
        "startsExpr": true,
        "rightAssociative": false,
        "isLoop": false,
        "isAssign": false,
        "prefix": false,
        "postfix": false,
        "binop": null
      },
      "value": "curryN",
      "start": 631,
      "end": 637,
      "loc": {
        "start": {
          "line": 19,
          "column": 15
        },
        "end": {
          "line": 19,
          "column": 21
        }
      }
    },
    {
      "type": {
        "label": "(",
        "beforeExpr": true,
        "startsExpr": true,
        "rightAssociative": false,
        "isLoop": false,
        "isAssign": false,
        "prefix": false,
        "postfix": false,
        "binop": null
      },
      "start": 637,
      "end": 638,
      "loc": {
        "start": {
          "line": 19,
          "column": 21
        },
        "end": {
          "line": 19,
          "column": 22
        }
      }
    },
    {
      "type": {
        "label": "num",
        "beforeExpr": false,
        "startsExpr": true,
        "rightAssociative": false,
        "isLoop": false,
        "isAssign": false,
        "prefix": false,
        "postfix": false,
        "binop": null,
        "updateContext": null
      },
      "value": 2,
      "start": 638,
      "end": 639,
      "loc": {
        "start": {
          "line": 19,
          "column": 22
        },
        "end": {
          "line": 19,
          "column": 23
        }
      }
    },
    {
      "type": {
        "label": ",",
        "beforeExpr": true,
        "startsExpr": false,
        "rightAssociative": false,
        "isLoop": false,
        "isAssign": false,
        "prefix": false,
        "postfix": false,
        "binop": null,
        "updateContext": null
      },
      "start": 639,
      "end": 640,
      "loc": {
        "start": {
          "line": 19,
          "column": 23
        },
        "end": {
          "line": 19,
          "column": 24
        }
      }
    },
    {
      "type": {
        "label": "(",
        "beforeExpr": true,
        "startsExpr": true,
        "rightAssociative": false,
        "isLoop": false,
        "isAssign": false,
        "prefix": false,
        "postfix": false,
        "binop": null
      },
      "start": 641,
      "end": 642,
      "loc": {
        "start": {
          "line": 19,
          "column": 25
        },
        "end": {
          "line": 19,
          "column": 26
        }
      }
    },
    {
      "type": {
        "label": "name",
        "beforeExpr": false,
        "startsExpr": true,
        "rightAssociative": false,
        "isLoop": false,
        "isAssign": false,
        "prefix": false,
        "postfix": false,
        "binop": null
      },
      "value": "fns",
      "start": 642,
      "end": 645,
      "loc": {
        "start": {
          "line": 19,
          "column": 26
        },
        "end": {
          "line": 19,
          "column": 29
        }
      }
    },
    {
      "type": {
        "label": ",",
        "beforeExpr": true,
        "startsExpr": false,
        "rightAssociative": false,
        "isLoop": false,
        "isAssign": false,
        "prefix": false,
        "postfix": false,
        "binop": null,
        "updateContext": null
      },
      "start": 645,
      "end": 646,
      "loc": {
        "start": {
          "line": 19,
          "column": 29
        },
        "end": {
          "line": 19,
          "column": 30
        }
      }
    },
    {
      "type": {
        "label": "...",
        "beforeExpr": true,
        "startsExpr": false,
        "rightAssociative": false,
        "isLoop": false,
        "isAssign": false,
        "prefix": false,
        "postfix": false,
        "binop": null,
        "updateContext": null
      },
      "start": 647,
      "end": 650,
      "loc": {
        "start": {
          "line": 19,
          "column": 31
        },
        "end": {
          "line": 19,
          "column": 34
        }
      }
    },
    {
      "type": {
        "label": "name",
        "beforeExpr": false,
        "startsExpr": true,
        "rightAssociative": false,
        "isLoop": false,
        "isAssign": false,
        "prefix": false,
        "postfix": false,
        "binop": null
      },
      "value": "args",
      "start": 650,
      "end": 654,
      "loc": {
        "start": {
          "line": 19,
          "column": 34
        },
        "end": {
          "line": 19,
          "column": 38
        }
      }
    },
    {
      "type": {
        "label": ")",
        "beforeExpr": false,
        "startsExpr": false,
        "rightAssociative": false,
        "isLoop": false,
        "isAssign": false,
        "prefix": false,
        "postfix": false,
        "binop": null
      },
      "start": 654,
      "end": 655,
      "loc": {
        "start": {
          "line": 19,
          "column": 38
        },
        "end": {
          "line": 19,
          "column": 39
        }
      }
    },
    {
      "type": {
        "label": "=>",
        "beforeExpr": true,
        "startsExpr": false,
        "rightAssociative": false,
        "isLoop": false,
        "isAssign": false,
        "prefix": false,
        "postfix": false,
        "binop": null,
        "updateContext": null
      },
      "start": 656,
      "end": 658,
      "loc": {
        "start": {
          "line": 19,
          "column": 40
        },
        "end": {
          "line": 19,
          "column": 42
        }
      }
    },
    {
      "type": {
        "label": "{",
        "beforeExpr": true,
        "startsExpr": true,
        "rightAssociative": false,
        "isLoop": false,
        "isAssign": false,
        "prefix": false,
        "postfix": false,
        "binop": null
      },
      "start": 659,
      "end": 660,
      "loc": {
        "start": {
          "line": 19,
          "column": 43
        },
        "end": {
          "line": 19,
          "column": 44
        }
      }
    },
    {
      "type": {
        "label": "for",
        "keyword": "for",
        "beforeExpr": false,
        "startsExpr": false,
        "rightAssociative": false,
        "isLoop": true,
        "isAssign": false,
        "prefix": false,
        "postfix": false,
        "binop": null,
        "updateContext": null
      },
      "value": "for",
      "start": 665,
      "end": 668,
      "loc": {
        "start": {
          "line": 20,
          "column": 4
        },
        "end": {
          "line": 20,
          "column": 7
        }
      }
    },
    {
      "type": {
        "label": "(",
        "beforeExpr": true,
        "startsExpr": true,
        "rightAssociative": false,
        "isLoop": false,
        "isAssign": false,
        "prefix": false,
        "postfix": false,
        "binop": null
      },
      "start": 669,
      "end": 670,
      "loc": {
        "start": {
          "line": 20,
          "column": 8
        },
        "end": {
          "line": 20,
          "column": 9
        }
      }
    },
    {
      "type": {
        "label": "let",
        "keyword": "let",
        "beforeExpr": false,
        "startsExpr": false,
        "rightAssociative": false,
        "isLoop": false,
        "isAssign": false,
        "prefix": false,
        "postfix": false,
        "binop": null,
        "updateContext": null
      },
      "value": "let",
      "start": 670,
      "end": 673,
      "loc": {
        "start": {
          "line": 20,
          "column": 9
        },
        "end": {
          "line": 20,
          "column": 12
        }
      }
    },
    {
      "type": {
        "label": "name",
        "beforeExpr": false,
        "startsExpr": true,
        "rightAssociative": false,
        "isLoop": false,
        "isAssign": false,
        "prefix": false,
        "postfix": false,
        "binop": null
      },
      "value": "i",
      "start": 674,
      "end": 675,
      "loc": {
        "start": {
          "line": 20,
          "column": 13
        },
        "end": {
          "line": 20,
          "column": 14
        }
      }
    },
    {
      "type": {
        "label": "=",
        "beforeExpr": true,
        "startsExpr": false,
        "rightAssociative": false,
        "isLoop": false,
        "isAssign": true,
        "prefix": false,
        "postfix": false,
        "binop": null,
        "updateContext": null
      },
      "value": "=",
      "start": 676,
      "end": 677,
      "loc": {
        "start": {
          "line": 20,
          "column": 15
        },
        "end": {
          "line": 20,
          "column": 16
        }
      }
    },
    {
      "type": {
        "label": "num",
        "beforeExpr": false,
        "startsExpr": true,
        "rightAssociative": false,
        "isLoop": false,
        "isAssign": false,
        "prefix": false,
        "postfix": false,
        "binop": null,
        "updateContext": null
      },
      "value": 0,
      "start": 678,
      "end": 679,
      "loc": {
        "start": {
          "line": 20,
          "column": 17
        },
        "end": {
          "line": 20,
          "column": 18
        }
      }
    },
    {
      "type": {
        "label": ";",
        "beforeExpr": true,
        "startsExpr": false,
        "rightAssociative": false,
        "isLoop": false,
        "isAssign": false,
        "prefix": false,
        "postfix": false,
        "binop": null,
        "updateContext": null
      },
      "start": 679,
      "end": 680,
      "loc": {
        "start": {
          "line": 20,
          "column": 18
        },
        "end": {
          "line": 20,
          "column": 19
        }
      }
    },
    {
      "type": {
        "label": "name",
        "beforeExpr": false,
        "startsExpr": true,
        "rightAssociative": false,
        "isLoop": false,
        "isAssign": false,
        "prefix": false,
        "postfix": false,
        "binop": null
      },
      "value": "i",
      "start": 681,
      "end": 682,
      "loc": {
        "start": {
          "line": 20,
          "column": 20
        },
        "end": {
          "line": 20,
          "column": 21
        }
      }
    },
    {
      "type": {
        "label": "</>",
        "beforeExpr": true,
        "startsExpr": false,
        "rightAssociative": false,
        "isLoop": false,
        "isAssign": false,
        "prefix": false,
        "postfix": false,
        "binop": 7,
        "updateContext": null
      },
      "value": "<",
      "start": 683,
      "end": 684,
      "loc": {
        "start": {
          "line": 20,
          "column": 22
        },
        "end": {
          "line": 20,
          "column": 23
        }
      }
    },
    {
      "type": {
        "label": "name",
        "beforeExpr": false,
        "startsExpr": true,
        "rightAssociative": false,
        "isLoop": false,
        "isAssign": false,
        "prefix": false,
        "postfix": false,
        "binop": null
      },
      "value": "fns",
      "start": 685,
      "end": 688,
      "loc": {
        "start": {
          "line": 20,
          "column": 24
        },
        "end": {
          "line": 20,
          "column": 27
        }
      }
    },
    {
      "type": {
        "label": ".",
        "beforeExpr": false,
        "startsExpr": false,
        "rightAssociative": false,
        "isLoop": false,
        "isAssign": false,
        "prefix": false,
        "postfix": false,
        "binop": null,
        "updateContext": null
      },
      "start": 688,
      "end": 689,
      "loc": {
        "start": {
          "line": 20,
          "column": 27
        },
        "end": {
          "line": 20,
          "column": 28
        }
      }
    },
    {
      "type": {
        "label": "name",
        "beforeExpr": false,
        "startsExpr": true,
        "rightAssociative": false,
        "isLoop": false,
        "isAssign": false,
        "prefix": false,
        "postfix": false,
        "binop": null
      },
      "value": "length",
      "start": 689,
      "end": 695,
      "loc": {
        "start": {
          "line": 20,
          "column": 28
        },
        "end": {
          "line": 20,
          "column": 34
        }
      }
    },
    {
      "type": {
        "label": ";",
        "beforeExpr": true,
        "startsExpr": false,
        "rightAssociative": false,
        "isLoop": false,
        "isAssign": false,
        "prefix": false,
        "postfix": false,
        "binop": null,
        "updateContext": null
      },
      "start": 695,
      "end": 696,
      "loc": {
        "start": {
          "line": 20,
          "column": 34
        },
        "end": {
          "line": 20,
          "column": 35
        }
      }
    },
    {
      "type": {
        "label": "name",
        "beforeExpr": false,
        "startsExpr": true,
        "rightAssociative": false,
        "isLoop": false,
        "isAssign": false,
        "prefix": false,
        "postfix": false,
        "binop": null
      },
      "value": "i",
      "start": 697,
      "end": 698,
      "loc": {
        "start": {
          "line": 20,
          "column": 36
        },
        "end": {
          "line": 20,
          "column": 37
        }
      }
    },
    {
      "type": {
        "label": "++/--",
        "beforeExpr": false,
        "startsExpr": true,
        "rightAssociative": false,
        "isLoop": false,
        "isAssign": false,
        "prefix": true,
        "postfix": true,
        "binop": null
      },
      "value": "++",
      "start": 698,
      "end": 700,
      "loc": {
        "start": {
          "line": 20,
          "column": 37
        },
        "end": {
          "line": 20,
          "column": 39
        }
      }
    },
    {
      "type": {
        "label": ")",
        "beforeExpr": false,
        "startsExpr": false,
        "rightAssociative": false,
        "isLoop": false,
        "isAssign": false,
        "prefix": false,
        "postfix": false,
        "binop": null
      },
      "start": 700,
      "end": 701,
      "loc": {
        "start": {
          "line": 20,
          "column": 39
        },
        "end": {
          "line": 20,
          "column": 40
        }
      }
    },
    {
      "type": {
        "label": "{",
        "beforeExpr": true,
        "startsExpr": true,
        "rightAssociative": false,
        "isLoop": false,
        "isAssign": false,
        "prefix": false,
        "postfix": false,
        "binop": null
      },
      "start": 702,
      "end": 703,
      "loc": {
        "start": {
          "line": 20,
          "column": 41
        },
        "end": {
          "line": 20,
          "column": 42
        }
      }
    },
    {
      "type": {
        "label": "if",
        "keyword": "if",
        "beforeExpr": false,
        "startsExpr": false,
        "rightAssociative": false,
        "isLoop": false,
        "isAssign": false,
        "prefix": false,
        "postfix": false,
        "binop": null,
        "updateContext": null
      },
      "value": "if",
      "start": 712,
      "end": 714,
      "loc": {
        "start": {
          "line": 21,
          "column": 8
        },
        "end": {
          "line": 21,
          "column": 10
        }
      }
    },
    {
      "type": {
        "label": "(",
        "beforeExpr": true,
        "startsExpr": true,
        "rightAssociative": false,
        "isLoop": false,
        "isAssign": false,
        "prefix": false,
        "postfix": false,
        "binop": null
      },
      "start": 715,
      "end": 716,
      "loc": {
        "start": {
          "line": 21,
          "column": 11
        },
        "end": {
          "line": 21,
          "column": 12
        }
      }
    },
    {
      "type": {
        "label": "prefix",
        "beforeExpr": true,
        "startsExpr": true,
        "rightAssociative": false,
        "isLoop": false,
        "isAssign": false,
        "prefix": true,
        "postfix": false,
        "binop": null,
        "updateContext": null
      },
      "value": "!",
      "start": 716,
      "end": 717,
      "loc": {
        "start": {
          "line": 21,
          "column": 12
        },
        "end": {
          "line": 21,
          "column": 13
        }
      }
    },
    {
      "type": {
        "label": "name",
        "beforeExpr": false,
        "startsExpr": true,
        "rightAssociative": false,
        "isLoop": false,
        "isAssign": false,
        "prefix": false,
        "postfix": false,
        "binop": null
      },
      "value": "fns",
      "start": 717,
      "end": 720,
      "loc": {
        "start": {
          "line": 21,
          "column": 13
        },
        "end": {
          "line": 21,
          "column": 16
        }
      }
    },
    {
      "type": {
        "label": "[",
        "beforeExpr": true,
        "startsExpr": true,
        "rightAssociative": false,
        "isLoop": false,
        "isAssign": false,
        "prefix": false,
        "postfix": false,
        "binop": null,
        "updateContext": null
      },
      "start": 720,
      "end": 721,
      "loc": {
        "start": {
          "line": 21,
          "column": 16
        },
        "end": {
          "line": 21,
          "column": 17
        }
      }
    },
    {
      "type": {
        "label": "name",
        "beforeExpr": false,
        "startsExpr": true,
        "rightAssociative": false,
        "isLoop": false,
        "isAssign": false,
        "prefix": false,
        "postfix": false,
        "binop": null
      },
      "value": "i",
      "start": 721,
      "end": 722,
      "loc": {
        "start": {
          "line": 21,
          "column": 17
        },
        "end": {
          "line": 21,
          "column": 18
        }
      }
    },
    {
      "type": {
        "label": "]",
        "beforeExpr": false,
        "startsExpr": false,
        "rightAssociative": false,
        "isLoop": false,
        "isAssign": false,
        "prefix": false,
        "postfix": false,
        "binop": null,
        "updateContext": null
      },
      "start": 722,
      "end": 723,
      "loc": {
        "start": {
          "line": 21,
          "column": 18
        },
        "end": {
          "line": 21,
          "column": 19
        }
      }
    },
    {
      "type": {
        "label": "(",
        "beforeExpr": true,
        "startsExpr": true,
        "rightAssociative": false,
        "isLoop": false,
        "isAssign": false,
        "prefix": false,
        "postfix": false,
        "binop": null
      },
      "start": 723,
      "end": 724,
      "loc": {
        "start": {
          "line": 21,
          "column": 19
        },
        "end": {
          "line": 21,
          "column": 20
        }
      }
    },
    {
      "type": {
        "label": "...",
        "beforeExpr": true,
        "startsExpr": false,
        "rightAssociative": false,
        "isLoop": false,
        "isAssign": false,
        "prefix": false,
        "postfix": false,
        "binop": null,
        "updateContext": null
      },
      "start": 724,
      "end": 727,
      "loc": {
        "start": {
          "line": 21,
          "column": 20
        },
        "end": {
          "line": 21,
          "column": 23
        }
      }
    },
    {
      "type": {
        "label": "name",
        "beforeExpr": false,
        "startsExpr": true,
        "rightAssociative": false,
        "isLoop": false,
        "isAssign": false,
        "prefix": false,
        "postfix": false,
        "binop": null
      },
      "value": "args",
      "start": 727,
      "end": 731,
      "loc": {
        "start": {
          "line": 21,
          "column": 23
        },
        "end": {
          "line": 21,
          "column": 27
        }
      }
    },
    {
      "type": {
        "label": ")",
        "beforeExpr": false,
        "startsExpr": false,
        "rightAssociative": false,
        "isLoop": false,
        "isAssign": false,
        "prefix": false,
        "postfix": false,
        "binop": null
      },
      "start": 731,
      "end": 732,
      "loc": {
        "start": {
          "line": 21,
          "column": 27
        },
        "end": {
          "line": 21,
          "column": 28
        }
      }
    },
    {
      "type": {
        "label": ")",
        "beforeExpr": false,
        "startsExpr": false,
        "rightAssociative": false,
        "isLoop": false,
        "isAssign": false,
        "prefix": false,
        "postfix": false,
        "binop": null
      },
      "start": 732,
      "end": 733,
      "loc": {
        "start": {
          "line": 21,
          "column": 28
        },
        "end": {
          "line": 21,
          "column": 29
        }
      }
    },
    {
      "type": {
        "label": "{",
        "beforeExpr": true,
        "startsExpr": true,
        "rightAssociative": false,
        "isLoop": false,
        "isAssign": false,
        "prefix": false,
        "postfix": false,
        "binop": null
      },
      "start": 734,
      "end": 735,
      "loc": {
        "start": {
          "line": 21,
          "column": 30
        },
        "end": {
          "line": 21,
          "column": 31
        }
      }
    },
    {
      "type": {
        "label": "return",
        "keyword": "return",
        "beforeExpr": true,
        "startsExpr": false,
        "rightAssociative": false,
        "isLoop": false,
        "isAssign": false,
        "prefix": false,
        "postfix": false,
        "binop": null,
        "updateContext": null
      },
      "value": "return",
      "start": 748,
      "end": 754,
      "loc": {
        "start": {
          "line": 22,
          "column": 12
        },
        "end": {
          "line": 22,
          "column": 18
        }
      }
    },
    {
      "type": {
        "label": "false",
        "keyword": "false",
        "beforeExpr": false,
        "startsExpr": true,
        "rightAssociative": false,
        "isLoop": false,
        "isAssign": false,
        "prefix": false,
        "postfix": false,
        "binop": null,
        "updateContext": null
      },
      "value": "false",
      "start": 755,
      "end": 760,
      "loc": {
        "start": {
          "line": 22,
          "column": 19
        },
        "end": {
          "line": 22,
          "column": 24
        }
      }
    },
    {
      "type": {
        "label": ";",
        "beforeExpr": true,
        "startsExpr": false,
        "rightAssociative": false,
        "isLoop": false,
        "isAssign": false,
        "prefix": false,
        "postfix": false,
        "binop": null,
        "updateContext": null
      },
      "start": 760,
      "end": 761,
      "loc": {
        "start": {
          "line": 22,
          "column": 24
        },
        "end": {
          "line": 22,
          "column": 25
        }
      }
    },
    {
      "type": {
        "label": "}",
        "beforeExpr": false,
        "startsExpr": false,
        "rightAssociative": false,
        "isLoop": false,
        "isAssign": false,
        "prefix": false,
        "postfix": false,
        "binop": null
      },
      "start": 770,
      "end": 771,
      "loc": {
        "start": {
          "line": 23,
          "column": 8
        },
        "end": {
          "line": 23,
          "column": 9
        }
      }
    },
    {
      "type": {
        "label": "}",
        "beforeExpr": false,
        "startsExpr": false,
        "rightAssociative": false,
        "isLoop": false,
        "isAssign": false,
        "prefix": false,
        "postfix": false,
        "binop": null
      },
      "start": 776,
      "end": 777,
      "loc": {
        "start": {
          "line": 24,
          "column": 4
        },
        "end": {
          "line": 24,
          "column": 5
        }
      }
    },
    {
      "type": {
        "label": "return",
        "keyword": "return",
        "beforeExpr": true,
        "startsExpr": false,
        "rightAssociative": false,
        "isLoop": false,
        "isAssign": false,
        "prefix": false,
        "postfix": false,
        "binop": null,
        "updateContext": null
      },
      "value": "return",
      "start": 782,
      "end": 788,
      "loc": {
        "start": {
          "line": 25,
          "column": 4
        },
        "end": {
          "line": 25,
          "column": 10
        }
      }
    },
    {
      "type": {
        "label": "true",
        "keyword": "true",
        "beforeExpr": false,
        "startsExpr": true,
        "rightAssociative": false,
        "isLoop": false,
        "isAssign": false,
        "prefix": false,
        "postfix": false,
        "binop": null,
        "updateContext": null
      },
      "value": "true",
      "start": 789,
      "end": 793,
      "loc": {
        "start": {
          "line": 25,
          "column": 11
        },
        "end": {
          "line": 25,
          "column": 15
        }
      }
    },
    {
      "type": {
        "label": ";",
        "beforeExpr": true,
        "startsExpr": false,
        "rightAssociative": false,
        "isLoop": false,
        "isAssign": false,
        "prefix": false,
        "postfix": false,
        "binop": null,
        "updateContext": null
      },
      "start": 793,
      "end": 794,
      "loc": {
        "start": {
          "line": 25,
          "column": 15
        },
        "end": {
          "line": 25,
          "column": 16
        }
      }
    },
    {
      "type": {
        "label": "}",
        "beforeExpr": false,
        "startsExpr": false,
        "rightAssociative": false,
        "isLoop": false,
        "isAssign": false,
        "prefix": false,
        "postfix": false,
        "binop": null
      },
      "start": 795,
      "end": 796,
      "loc": {
        "start": {
          "line": 26,
          "column": 0
        },
        "end": {
          "line": 26,
          "column": 1
        }
      }
    },
    {
      "type": {
        "label": ")",
        "beforeExpr": false,
        "startsExpr": false,
        "rightAssociative": false,
        "isLoop": false,
        "isAssign": false,
        "prefix": false,
        "postfix": false,
        "binop": null
      },
      "start": 796,
      "end": 797,
      "loc": {
        "start": {
          "line": 26,
          "column": 1
        },
        "end": {
          "line": 26,
          "column": 2
        }
      }
    },
    {
      "type": {
        "label": ";",
        "beforeExpr": true,
        "startsExpr": false,
        "rightAssociative": false,
        "isLoop": false,
        "isAssign": false,
        "prefix": false,
        "postfix": false,
        "binop": null,
        "updateContext": null
      },
      "start": 797,
      "end": 798,
      "loc": {
        "start": {
          "line": 26,
          "column": 2
        },
        "end": {
          "line": 26,
          "column": 3
        }
      }
    },
    {
      "type": {
        "label": "eof",
        "beforeExpr": false,
        "startsExpr": false,
        "rightAssociative": false,
        "isLoop": false,
        "isAssign": false,
        "prefix": false,
        "postfix": false,
        "binop": null,
        "updateContext": null
      },
      "start": 799,
      "end": 799,
      "loc": {
        "start": {
          "line": 27,
          "column": 0
        },
        "end": {
          "line": 27,
          "column": 0
        }
      }
    }
  ]
}