{
  "type": "File",
  "start": 0,
  "end": 571,
  "loc": {
    "start": {
      "line": 1,
      "column": 0
    },
    "end": {
      "line": 19,
      "column": 0
    }
  },
  "program": {
    "type": "Program",
    "start": 0,
    "end": 571,
    "loc": {
      "start": {
        "line": 1,
        "column": 0
      },
      "end": {
        "line": 19,
        "column": 0
      }
    },
    "sourceType": "module",
    "body": [
      {
        "type": "ImportDeclaration",
        "start": 0,
        "end": 30,
        "loc": {
          "start": {
            "line": 1,
            "column": 0
          },
          "end": {
            "line": 1,
            "column": 30
          }
        },
        "specifiers": [
          {
            "type": "ImportDefaultSpecifier",
            "start": 7,
            "end": 13,
            "loc": {
              "start": {
                "line": 1,
                "column": 7
              },
              "end": {
                "line": 1,
                "column": 13
              }
            },
            "local": {
              "type": "Identifier",
              "start": 7,
              "end": 13,
              "loc": {
                "start": {
                  "line": 1,
                  "column": 7
                },
                "end": {
                  "line": 1,
                  "column": 13
                },
                "identifierName": "curryN"
              },
              "name": "curryN"
            }
          }
        ],
        "source": {
          "type": "StringLiteral",
          "start": 19,
          "end": 29,
          "loc": {
            "start": {
              "line": 1,
              "column": 19
            },
            "end": {
              "line": 1,
              "column": 29
            }
          },
          "extra": {
            "rawValue": "./curryN",
            "raw": "'./curryN'"
          },
          "value": "./curryN"
        },
        "trailingComments": [
          {
            "type": "CommentBlock",
            "value": "*\r\n * If `test` is function it calls with applied first argument, otherwise just returns `test`\r\n *\r\n * @param {Array} args Arguments passed to `test` if it's a function\r\n * @param {*} test if `test` is function it's called with `args`\r\n * @return {*}\r\n * @example\r\n *\r\n *      applyOrReturn([1,2,3], (...args) => args) // => [1,2,3]\r\n *      applyOrReturn([1,2,3], 'test') // => 'test'\r\n ",
            "start": 32,
            "end": 425,
            "loc": {
              "start": {
                "line": 2,
                "column": 0
              },
              "end": {
                "line": 12,
                "column": 3
              }
            }
          }
        ]
      },
      {
        "type": "ExportDefaultDeclaration",
        "start": 427,
        "end": 569,
        "loc": {
          "start": {
            "line": 13,
            "column": 0
          },
          "end": {
            "line": 18,
            "column": 3
          }
        },
        "declaration": {
          "type": "ArrowFunctionExpression",
          "start": 452,
          "end": 567,
          "loc": {
            "start": {
              "line": 13,
              "column": 25
            },
            "end": {
              "line": 18,
              "column": 1
            }
          },
          "id": null,
          "generator": false,
          "expression": false,
          "async": false,
          "params": [
            {
              "type": "Identifier",
              "start": 453,
              "end": 457,
              "loc": {
                "start": {
                  "line": 13,
                  "column": 26
                },
                "end": {
                  "line": 13,
                  "column": 30
                },
                "identifierName": "args"
              },
              "name": "args"
            },
            {
              "type": "Identifier",
              "start": 459,
              "end": 463,
              "loc": {
                "start": {
                  "line": 13,
                  "column": 32
                },
                "end": {
                  "line": 13,
                  "column": 36
                },
                "identifierName": "test"
              },
              "name": "test"
            }
          ],
          "body": {
            "type": "BlockStatement",
            "start": 468,
            "end": 567,
            "loc": {
              "start": {
                "line": 13,
                "column": 41
              },
              "end": {
                "line": 18,
                "column": 1
              }
            },
            "body": [
              {
                "type": "IfStatement",
                "start": 475,
                "end": 546,
                "loc": {
                  "start": {
                    "line": 14,
                    "column": 4
                  },
                  "end": {
                    "line": 16,
                    "column": 5
                  }
                },
                "test": {
                  "type": "BinaryExpression",
                  "start": 479,
                  "end": 505,
                  "loc": {
                    "start": {
                      "line": 14,
                      "column": 8
                    },
                    "end": {
                      "line": 14,
                      "column": 34
                    }
                  },
                  "left": {
                    "type": "UnaryExpression",
                    "start": 479,
                    "end": 490,
                    "loc": {
                      "start": {
                        "line": 14,
                        "column": 8
                      },
                      "end": {
                        "line": 14,
                        "column": 19
                      }
                    },
                    "operator": "typeof",
                    "prefix": true,
                    "argument": {
                      "type": "Identifier",
                      "start": 486,
                      "end": 490,
                      "loc": {
                        "start": {
                          "line": 14,
                          "column": 15
                        },
                        "end": {
                          "line": 14,
                          "column": 19
                        },
                        "identifierName": "test"
                      },
                      "name": "test"
                    },
                    "extra": {
                      "parenthesizedArgument": false
                    }
                  },
                  "operator": "===",
                  "right": {
                    "type": "StringLiteral",
                    "start": 495,
                    "end": 505,
                    "loc": {
                      "start": {
                        "line": 14,
                        "column": 24
                      },
                      "end": {
                        "line": 14,
                        "column": 34
                      }
                    },
                    "extra": {
                      "rawValue": "function",
                      "raw": "'function'"
                    },
                    "value": "function"
                  }
                },
                "consequent": {
                  "type": "BlockStatement",
                  "start": 507,
                  "end": 546,
                  "loc": {
                    "start": {
                      "line": 14,
                      "column": 36
                    },
                    "end": {
                      "line": 16,
                      "column": 5
                    }
                  },
                  "body": [
                    {
                      "type": "ReturnStatement",
                      "start": 518,
                      "end": 539,
                      "loc": {
                        "start": {
                          "line": 15,
                          "column": 8
                        },
                        "end": {
                          "line": 15,
                          "column": 29
                        }
                      },
                      "argument": {
                        "type": "CallExpression",
                        "start": 525,
                        "end": 538,
                        "loc": {
                          "start": {
                            "line": 15,
                            "column": 15
                          },
                          "end": {
                            "line": 15,
                            "column": 28
                          }
                        },
                        "callee": {
                          "type": "Identifier",
                          "start": 525,
                          "end": 529,
                          "loc": {
                            "start": {
                              "line": 15,
                              "column": 15
                            },
                            "end": {
                              "line": 15,
                              "column": 19
                            },
                            "identifierName": "test"
                          },
                          "name": "test"
                        },
                        "arguments": [
                          {
                            "type": "SpreadElement",
                            "start": 530,
                            "end": 537,
                            "loc": {
                              "start": {
                                "line": 15,
                                "column": 20
                              },
                              "end": {
                                "line": 15,
                                "column": 27
                              }
                            },
                            "argument": {
                              "type": "Identifier",
                              "start": 533,
                              "end": 537,
                              "loc": {
                                "start": {
                                  "line": 15,
                                  "column": 23
                                },
                                "end": {
                                  "line": 15,
                                  "column": 27
                                },
                                "identifierName": "args"
                              },
                              "name": "args"
                            }
                          }
                        ]
                      }
                    }
                  ],
                  "directives": []
                },
                "alternate": null
              },
              {
                "type": "ReturnStatement",
                "start": 552,
                "end": 564,
                "loc": {
                  "start": {
                    "line": 17,
                    "column": 4
                  },
                  "end": {
                    "line": 17,
                    "column": 16
                  }
                },
                "argument": {
                  "type": "Identifier",
                  "start": 559,
                  "end": 563,
                  "loc": {
                    "start": {
                      "line": 17,
                      "column": 11
                    },
                    "end": {
                      "line": 17,
                      "column": 15
                    },
                    "identifierName": "test"
                  },
                  "name": "test"
                }
              }
            ],
            "directives": []
          },
          "_curryN": 2,
          "leadingComments": [
            {
              "type": "CommentBlock",
              "value": "*\r\n * If `test` is function it calls with applied first argument, otherwise just returns `test`\r\n *\r\n * @param {Array} args Arguments passed to `test` if it's a function\r\n * @param {*} test if `test` is function it's called with `args`\r\n * @return {*}\r\n * @example\r\n *\r\n *      applyOrReturn([1,2,3], (...args) => args) // => [1,2,3]\r\n *      applyOrReturn([1,2,3], 'test') // => 'test'\r\n ",
              "start": 32,
              "end": 425,
              "loc": {
                "start": {
                  "line": 2,
                  "column": 0
                },
                "end": {
                  "line": 12,
                  "column": 3
                }
              }
            }
          ],
          "trailingComments": []
        },
        "leadingComments": [
          {
            "type": "CommentBlock",
            "value": "*\r\n * If `test` is function it calls with applied first argument, otherwise just returns `test`\r\n *\r\n * @param {Array} args Arguments passed to `test` if it's a function\r\n * @param {*} test if `test` is function it's called with `args`\r\n * @return {*}\r\n * @example\r\n *\r\n *      applyOrReturn([1,2,3], (...args) => args) // => [1,2,3]\r\n *      applyOrReturn([1,2,3], 'test') // => 'test'\r\n ",
            "start": 32,
            "end": 425,
            "loc": {
              "start": {
                "line": 2,
                "column": 0
              },
              "end": {
                "line": 12,
                "column": 3
              }
            }
          }
        ]
      }
    ],
    "directives": []
  },
  "comments": [
    {
      "type": "CommentBlock",
      "value": "*\r\n * If `test` is function it calls with applied first argument, otherwise just returns `test`\r\n *\r\n * @param {Array} args Arguments passed to `test` if it's a function\r\n * @param {*} test if `test` is function it's called with `args`\r\n * @return {*}\r\n * @example\r\n *\r\n *      applyOrReturn([1,2,3], (...args) => args) // => [1,2,3]\r\n *      applyOrReturn([1,2,3], 'test') // => 'test'\r\n ",
      "start": 32,
      "end": 425,
      "loc": {
        "start": {
          "line": 2,
          "column": 0
        },
        "end": {
          "line": 12,
          "column": 3
        }
      }
    }
  ],
  "tokens": [
    {
      "type": {
        "label": "import",
        "keyword": "import",
        "beforeExpr": false,
        "startsExpr": true,
        "rightAssociative": false,
        "isLoop": false,
        "isAssign": false,
        "prefix": false,
        "postfix": false,
        "binop": null,
        "updateContext": null
      },
      "value": "import",
      "start": 0,
      "end": 6,
      "loc": {
        "start": {
          "line": 1,
          "column": 0
        },
        "end": {
          "line": 1,
          "column": 6
        }
      }
    },
    {
      "type": {
        "label": "name",
        "beforeExpr": false,
        "startsExpr": true,
        "rightAssociative": false,
        "isLoop": false,
        "isAssign": false,
        "prefix": false,
        "postfix": false,
        "binop": null
      },
      "value": "curryN",
      "start": 7,
      "end": 13,
      "loc": {
        "start": {
          "line": 1,
          "column": 7
        },
        "end": {
          "line": 1,
          "column": 13
        }
      }
    },
    {
      "type": {
        "label": "name",
        "beforeExpr": false,
        "startsExpr": true,
        "rightAssociative": false,
        "isLoop": false,
        "isAssign": false,
        "prefix": false,
        "postfix": false,
        "binop": null
      },
      "value": "from",
      "start": 14,
      "end": 18,
      "loc": {
        "start": {
          "line": 1,
          "column": 14
        },
        "end": {
          "line": 1,
          "column": 18
        }
      }
    },
    {
      "type": {
        "label": "string",
        "beforeExpr": false,
        "startsExpr": true,
        "rightAssociative": false,
        "isLoop": false,
        "isAssign": false,
        "prefix": false,
        "postfix": false,
        "binop": null,
        "updateContext": null
      },
      "value": "./curryN",
      "start": 19,
      "end": 29,
      "loc": {
        "start": {
          "line": 1,
          "column": 19
        },
        "end": {
          "line": 1,
          "column": 29
        }
      }
    },
    {
      "type": {
        "label": ";",
        "beforeExpr": true,
        "startsExpr": false,
        "rightAssociative": false,
        "isLoop": false,
        "isAssign": false,
        "prefix": false,
        "postfix": false,
        "binop": null,
        "updateContext": null
      },
      "start": 29,
      "end": 30,
      "loc": {
        "start": {
          "line": 1,
          "column": 29
        },
        "end": {
          "line": 1,
          "column": 30
        }
      }
    },
    {
      "type": "CommentBlock",
      "value": "*\r\n * If `test` is function it calls with applied first argument, otherwise just returns `test`\r\n *\r\n * @param {Array} args Arguments passed to `test` if it's a function\r\n * @param {*} test if `test` is function it's called with `args`\r\n * @return {*}\r\n * @example\r\n *\r\n *      applyOrReturn([1,2,3], (...args) => args) // => [1,2,3]\r\n *      applyOrReturn([1,2,3], 'test') // => 'test'\r\n ",
      "start": 32,
      "end": 425,
      "loc": {
        "start": {
          "line": 2,
          "column": 0
        },
        "end": {
          "line": 12,
          "column": 3
        }
      }
    },
    {
      "type": {
        "label": "export",
        "keyword": "export",
        "beforeExpr": false,
        "startsExpr": false,
        "rightAssociative": false,
        "isLoop": false,
        "isAssign": false,
        "prefix": false,
        "postfix": false,
        "binop": null,
        "updateContext": null
      },
      "value": "export",
      "start": 427,
      "end": 433,
      "loc": {
        "start": {
          "line": 13,
          "column": 0
        },
        "end": {
          "line": 13,
          "column": 6
        }
      }
    },
    {
      "type": {
        "label": "default",
        "keyword": "default",
        "beforeExpr": true,
        "startsExpr": false,
        "rightAssociative": false,
        "isLoop": false,
        "isAssign": false,
        "prefix": false,
        "postfix": false,
        "binop": null,
        "updateContext": null
      },
      "value": "default",
      "start": 434,
      "end": 441,
      "loc": {
        "start": {
          "line": 13,
          "column": 7
        },
        "end": {
          "line": 13,
          "column": 14
        }
      }
    },
    {
      "type": {
        "label": "name",
        "beforeExpr": false,
        "startsExpr": true,
        "rightAssociative": false,
        "isLoop": false,
        "isAssign": false,
        "prefix": false,
        "postfix": false,
        "binop": null
      },
      "value": "curryN",
      "start": 442,
      "end": 448,
      "loc": {
        "start": {
          "line": 13,
          "column": 15
        },
        "end": {
          "line": 13,
          "column": 21
        }
      }
    },
    {
      "type": {
        "label": "(",
        "beforeExpr": true,
        "startsExpr": true,
        "rightAssociative": false,
        "isLoop": false,
        "isAssign": false,
        "prefix": false,
        "postfix": false,
        "binop": null
      },
      "start": 448,
      "end": 449,
      "loc": {
        "start": {
          "line": 13,
          "column": 21
        },
        "end": {
          "line": 13,
          "column": 22
        }
      }
    },
    {
      "type": {
        "label": "num",
        "beforeExpr": false,
        "startsExpr": true,
        "rightAssociative": false,
        "isLoop": false,
        "isAssign": false,
        "prefix": false,
        "postfix": false,
        "binop": null,
        "updateContext": null
      },
      "value": 2,
      "start": 449,
      "end": 450,
      "loc": {
        "start": {
          "line": 13,
          "column": 22
        },
        "end": {
          "line": 13,
          "column": 23
        }
      }
    },
    {
      "type": {
        "label": ",",
        "beforeExpr": true,
        "startsExpr": false,
        "rightAssociative": false,
        "isLoop": false,
        "isAssign": false,
        "prefix": false,
        "postfix": false,
        "binop": null,
        "updateContext": null
      },
      "start": 450,
      "end": 451,
      "loc": {
        "start": {
          "line": 13,
          "column": 23
        },
        "end": {
          "line": 13,
          "column": 24
        }
      }
    },
    {
      "type": {
        "label": "(",
        "beforeExpr": true,
        "startsExpr": true,
        "rightAssociative": false,
        "isLoop": false,
        "isAssign": false,
        "prefix": false,
        "postfix": false,
        "binop": null
      },
      "start": 452,
      "end": 453,
      "loc": {
        "start": {
          "line": 13,
          "column": 25
        },
        "end": {
          "line": 13,
          "column": 26
        }
      }
    },
    {
      "type": {
        "label": "name",
        "beforeExpr": false,
        "startsExpr": true,
        "rightAssociative": false,
        "isLoop": false,
        "isAssign": false,
        "prefix": false,
        "postfix": false,
        "binop": null
      },
      "value": "args",
      "start": 453,
      "end": 457,
      "loc": {
        "start": {
          "line": 13,
          "column": 26
        },
        "end": {
          "line": 13,
          "column": 30
        }
      }
    },
    {
      "type": {
        "label": ",",
        "beforeExpr": true,
        "startsExpr": false,
        "rightAssociative": false,
        "isLoop": false,
        "isAssign": false,
        "prefix": false,
        "postfix": false,
        "binop": null,
        "updateContext": null
      },
      "start": 457,
      "end": 458,
      "loc": {
        "start": {
          "line": 13,
          "column": 30
        },
        "end": {
          "line": 13,
          "column": 31
        }
      }
    },
    {
      "type": {
        "label": "name",
        "beforeExpr": false,
        "startsExpr": true,
        "rightAssociative": false,
        "isLoop": false,
        "isAssign": false,
        "prefix": false,
        "postfix": false,
        "binop": null
      },
      "value": "test",
      "start": 459,
      "end": 463,
      "loc": {
        "start": {
          "line": 13,
          "column": 32
        },
        "end": {
          "line": 13,
          "column": 36
        }
      }
    },
    {
      "type": {
        "label": ")",
        "beforeExpr": false,
        "startsExpr": false,
        "rightAssociative": false,
        "isLoop": false,
        "isAssign": false,
        "prefix": false,
        "postfix": false,
        "binop": null
      },
      "start": 463,
      "end": 464,
      "loc": {
        "start": {
          "line": 13,
          "column": 36
        },
        "end": {
          "line": 13,
          "column": 37
        }
      }
    },
    {
      "type": {
        "label": "=>",
        "beforeExpr": true,
        "startsExpr": false,
        "rightAssociative": false,
        "isLoop": false,
        "isAssign": false,
        "prefix": false,
        "postfix": false,
        "binop": null,
        "updateContext": null
      },
      "start": 465,
      "end": 467,
      "loc": {
        "start": {
          "line": 13,
          "column": 38
        },
        "end": {
          "line": 13,
          "column": 40
        }
      }
    },
    {
      "type": {
        "label": "{",
        "beforeExpr": true,
        "startsExpr": true,
        "rightAssociative": false,
        "isLoop": false,
        "isAssign": false,
        "prefix": false,
        "postfix": false,
        "binop": null
      },
      "start": 468,
      "end": 469,
      "loc": {
        "start": {
          "line": 13,
          "column": 41
        },
        "end": {
          "line": 13,
          "column": 42
        }
      }
    },
    {
      "type": {
        "label": "if",
        "keyword": "if",
        "beforeExpr": false,
        "startsExpr": false,
        "rightAssociative": false,
        "isLoop": false,
        "isAssign": false,
        "prefix": false,
        "postfix": false,
        "binop": null,
        "updateContext": null
      },
      "value": "if",
      "start": 475,
      "end": 477,
      "loc": {
        "start": {
          "line": 14,
          "column": 4
        },
        "end": {
          "line": 14,
          "column": 6
        }
      }
    },
    {
      "type": {
        "label": "(",
        "beforeExpr": true,
        "startsExpr": true,
        "rightAssociative": false,
        "isLoop": false,
        "isAssign": false,
        "prefix": false,
        "postfix": false,
        "binop": null
      },
      "start": 478,
      "end": 479,
      "loc": {
        "start": {
          "line": 14,
          "column": 7
        },
        "end": {
          "line": 14,
          "column": 8
        }
      }
    },
    {
      "type": {
        "label": "typeof",
        "keyword": "typeof",
        "beforeExpr": true,
        "startsExpr": true,
        "rightAssociative": false,
        "isLoop": false,
        "isAssign": false,
        "prefix": true,
        "postfix": false,
        "binop": null,
        "updateContext": null
      },
      "value": "typeof",
      "start": 479,
      "end": 485,
      "loc": {
        "start": {
          "line": 14,
          "column": 8
        },
        "end": {
          "line": 14,
          "column": 14
        }
      }
    },
    {
      "type": {
        "label": "name",
        "beforeExpr": false,
        "startsExpr": true,
        "rightAssociative": false,
        "isLoop": false,
        "isAssign": false,
        "prefix": false,
        "postfix": false,
        "binop": null
      },
      "value": "test",
      "start": 486,
      "end": 490,
      "loc": {
        "start": {
          "line": 14,
          "column": 15
        },
        "end": {
          "line": 14,
          "column": 19
        }
      }
    },
    {
      "type": {
        "label": "==/!=",
        "beforeExpr": true,
        "startsExpr": false,
        "rightAssociative": false,
        "isLoop": false,
        "isAssign": false,
        "prefix": false,
        "postfix": false,
        "binop": 6,
        "updateContext": null
      },
      "value": "===",
      "start": 491,
      "end": 494,
      "loc": {
        "start": {
          "line": 14,
          "column": 20
        },
        "end": {
          "line": 14,
          "column": 23
        }
      }
    },
    {
      "type": {
        "label": "string",
        "beforeExpr": false,
        "startsExpr": true,
        "rightAssociative": false,
        "isLoop": false,
        "isAssign": false,
        "prefix": false,
        "postfix": false,
        "binop": null,
        "updateContext": null
      },
      "value": "function",
      "start": 495,
      "end": 505,
      "loc": {
        "start": {
          "line": 14,
          "column": 24
        },
        "end": {
          "line": 14,
          "column": 34
        }
      }
    },
    {
      "type": {
        "label": ")",
        "beforeExpr": false,
        "startsExpr": false,
        "rightAssociative": false,
        "isLoop": false,
        "isAssign": false,
        "prefix": false,
        "postfix": false,
        "binop": null
      },
      "start": 505,
      "end": 506,
      "loc": {
        "start": {
          "line": 14,
          "column": 34
        },
        "end": {
          "line": 14,
          "column": 35
        }
      }
    },
    {
      "type": {
        "label": "{",
        "beforeExpr": true,
        "startsExpr": true,
        "rightAssociative": false,
        "isLoop": false,
        "isAssign": false,
        "prefix": false,
        "postfix": false,
        "binop": null
      },
      "start": 507,
      "end": 508,
      "loc": {
        "start": {
          "line": 14,
          "column": 36
        },
        "end": {
          "line": 14,
          "column": 37
        }
      }
    },
    {
      "type": {
        "label": "return",
        "keyword": "return",
        "beforeExpr": true,
        "startsExpr": false,
        "rightAssociative": false,
        "isLoop": false,
        "isAssign": false,
        "prefix": false,
        "postfix": false,
        "binop": null,
        "updateContext": null
      },
      "value": "return",
      "start": 518,
      "end": 524,
      "loc": {
        "start": {
          "line": 15,
          "column": 8
        },
        "end": {
          "line": 15,
          "column": 14
        }
      }
    },
    {
      "type": {
        "label": "name",
        "beforeExpr": false,
        "startsExpr": true,
        "rightAssociative": false,
        "isLoop": false,
        "isAssign": false,
        "prefix": false,
        "postfix": false,
        "binop": null
      },
      "value": "test",
      "start": 525,
      "end": 529,
      "loc": {
        "start": {
          "line": 15,
          "column": 15
        },
        "end": {
          "line": 15,
          "column": 19
        }
      }
    },
    {
      "type": {
        "label": "(",
        "beforeExpr": true,
        "startsExpr": true,
        "rightAssociative": false,
        "isLoop": false,
        "isAssign": false,
        "prefix": false,
        "postfix": false,
        "binop": null
      },
      "start": 529,
      "end": 530,
      "loc": {
        "start": {
          "line": 15,
          "column": 19
        },
        "end": {
          "line": 15,
          "column": 20
        }
      }
    },
    {
      "type": {
        "label": "...",
        "beforeExpr": true,
        "startsExpr": false,
        "rightAssociative": false,
        "isLoop": false,
        "isAssign": false,
        "prefix": false,
        "postfix": false,
        "binop": null,
        "updateContext": null
      },
      "start": 530,
      "end": 533,
      "loc": {
        "start": {
          "line": 15,
          "column": 20
        },
        "end": {
          "line": 15,
          "column": 23
        }
      }
    },
    {
      "type": {
        "label": "name",
        "beforeExpr": false,
        "startsExpr": true,
        "rightAssociative": false,
        "isLoop": false,
        "isAssign": false,
        "prefix": false,
        "postfix": false,
        "binop": null
      },
      "value": "args",
      "start": 533,
      "end": 537,
      "loc": {
        "start": {
          "line": 15,
          "column": 23
        },
        "end": {
          "line": 15,
          "column": 27
        }
      }
    },
    {
      "type": {
        "label": ")",
        "beforeExpr": false,
        "startsExpr": false,
        "rightAssociative": false,
        "isLoop": false,
        "isAssign": false,
        "prefix": false,
        "postfix": false,
        "binop": null
      },
      "start": 537,
      "end": 538,
      "loc": {
        "start": {
          "line": 15,
          "column": 27
        },
        "end": {
          "line": 15,
          "column": 28
        }
      }
    },
    {
      "type": {
        "label": ";",
        "beforeExpr": true,
        "startsExpr": false,
        "rightAssociative": false,
        "isLoop": false,
        "isAssign": false,
        "prefix": false,
        "postfix": false,
        "binop": null,
        "updateContext": null
      },
      "start": 538,
      "end": 539,
      "loc": {
        "start": {
          "line": 15,
          "column": 28
        },
        "end": {
          "line": 15,
          "column": 29
        }
      }
    },
    {
      "type": {
        "label": "}",
        "beforeExpr": false,
        "startsExpr": false,
        "rightAssociative": false,
        "isLoop": false,
        "isAssign": false,
        "prefix": false,
        "postfix": false,
        "binop": null
      },
      "start": 545,
      "end": 546,
      "loc": {
        "start": {
          "line": 16,
          "column": 4
        },
        "end": {
          "line": 16,
          "column": 5
        }
      }
    },
    {
      "type": {
        "label": "return",
        "keyword": "return",
        "beforeExpr": true,
        "startsExpr": false,
        "rightAssociative": false,
        "isLoop": false,
        "isAssign": false,
        "prefix": false,
        "postfix": false,
        "binop": null,
        "updateContext": null
      },
      "value": "return",
      "start": 552,
      "end": 558,
      "loc": {
        "start": {
          "line": 17,
          "column": 4
        },
        "end": {
          "line": 17,
          "column": 10
        }
      }
    },
    {
      "type": {
        "label": "name",
        "beforeExpr": false,
        "startsExpr": true,
        "rightAssociative": false,
        "isLoop": false,
        "isAssign": false,
        "prefix": false,
        "postfix": false,
        "binop": null
      },
      "value": "test",
      "start": 559,
      "end": 563,
      "loc": {
        "start": {
          "line": 17,
          "column": 11
        },
        "end": {
          "line": 17,
          "column": 15
        }
      }
    },
    {
      "type": {
        "label": ";",
        "beforeExpr": true,
        "startsExpr": false,
        "rightAssociative": false,
        "isLoop": false,
        "isAssign": false,
        "prefix": false,
        "postfix": false,
        "binop": null,
        "updateContext": null
      },
      "start": 563,
      "end": 564,
      "loc": {
        "start": {
          "line": 17,
          "column": 15
        },
        "end": {
          "line": 17,
          "column": 16
        }
      }
    },
    {
      "type": {
        "label": "}",
        "beforeExpr": false,
        "startsExpr": false,
        "rightAssociative": false,
        "isLoop": false,
        "isAssign": false,
        "prefix": false,
        "postfix": false,
        "binop": null
      },
      "start": 566,
      "end": 567,
      "loc": {
        "start": {
          "line": 18,
          "column": 0
        },
        "end": {
          "line": 18,
          "column": 1
        }
      }
    },
    {
      "type": {
        "label": ")",
        "beforeExpr": false,
        "startsExpr": false,
        "rightAssociative": false,
        "isLoop": false,
        "isAssign": false,
        "prefix": false,
        "postfix": false,
        "binop": null
      },
      "start": 567,
      "end": 568,
      "loc": {
        "start": {
          "line": 18,
          "column": 1
        },
        "end": {
          "line": 18,
          "column": 2
        }
      }
    },
    {
      "type": {
        "label": ";",
        "beforeExpr": true,
        "startsExpr": false,
        "rightAssociative": false,
        "isLoop": false,
        "isAssign": false,
        "prefix": false,
        "postfix": false,
        "binop": null,
        "updateContext": null
      },
      "start": 568,
      "end": 569,
      "loc": {
        "start": {
          "line": 18,
          "column": 2
        },
        "end": {
          "line": 18,
          "column": 3
        }
      }
    },
    {
      "type": {
        "label": "eof",
        "beforeExpr": false,
        "startsExpr": false,
        "rightAssociative": false,
        "isLoop": false,
        "isAssign": false,
        "prefix": false,
        "postfix": false,
        "binop": null,
        "updateContext": null
      },
      "start": 571,
      "end": 571,
      "loc": {
        "start": {
          "line": 19,
          "column": 0
        },
        "end": {
          "line": 19,
          "column": 0
        }
      }
    }
  ]
}