{
  "type": "File",
  "start": 0,
  "end": 772,
  "loc": {
    "start": {
      "line": 1,
      "column": 0
    },
    "end": {
      "line": 22,
      "column": 0
    }
  },
  "program": {
    "type": "Program",
    "start": 0,
    "end": 772,
    "loc": {
      "start": {
        "line": 1,
        "column": 0
      },
      "end": {
        "line": 22,
        "column": 0
      }
    },
    "sourceType": "module",
    "body": [
      {
        "type": "ImportDeclaration",
        "start": 0,
        "end": 30,
        "loc": {
          "start": {
            "line": 1,
            "column": 0
          },
          "end": {
            "line": 1,
            "column": 30
          }
        },
        "specifiers": [
          {
            "type": "ImportDefaultSpecifier",
            "start": 7,
            "end": 13,
            "loc": {
              "start": {
                "line": 1,
                "column": 7
              },
              "end": {
                "line": 1,
                "column": 13
              }
            },
            "local": {
              "type": "Identifier",
              "start": 7,
              "end": 13,
              "loc": {
                "start": {
                  "line": 1,
                  "column": 7
                },
                "end": {
                  "line": 1,
                  "column": 13
                },
                "identifierName": "curryN"
              },
              "name": "curryN"
            }
          }
        ],
        "source": {
          "type": "StringLiteral",
          "start": 19,
          "end": 29,
          "loc": {
            "start": {
              "line": 1,
              "column": 19
            },
            "end": {
              "line": 1,
              "column": 29
            }
          },
          "extra": {
            "rawValue": "./curryN",
            "raw": "'./curryN'"
          },
          "value": "./curryN"
        },
        "trailingComments": [
          {
            "type": "CommentBlock",
            "value": "*\n * Creates a debounced function that delays invoking `func` until after `wait`\n * milliseconds have elapsed since the last time the debounced function was\n * invoked. Delayed function invocation might be cancelled by calling cancel method.\n *\n * @param {number} wait The number of milliseconds to delay.\n * @param {Function} fn The function to debounce.\n * @returns {Function} Returns the new debounced function.\n ",
            "start": 31,
            "end": 451,
            "loc": {
              "start": {
                "line": 2,
                "column": 0
              },
              "end": {
                "line": 10,
                "column": 3
              }
            }
          }
        ]
      },
      {
        "type": "ExportDefaultDeclaration",
        "start": 452,
        "end": 771,
        "loc": {
          "start": {
            "line": 11,
            "column": 0
          },
          "end": {
            "line": 21,
            "column": 3
          }
        },
        "declaration": {
          "type": "ArrowFunctionExpression",
          "start": 477,
          "end": 769,
          "loc": {
            "start": {
              "line": 11,
              "column": 25
            },
            "end": {
              "line": 21,
              "column": 1
            }
          },
          "id": null,
          "generator": false,
          "expression": false,
          "async": false,
          "params": [
            {
              "type": "Identifier",
              "start": 478,
              "end": 482,
              "loc": {
                "start": {
                  "line": 11,
                  "column": 26
                },
                "end": {
                  "line": 11,
                  "column": 30
                },
                "identifierName": "wait"
              },
              "name": "wait"
            },
            {
              "type": "Identifier",
              "start": 484,
              "end": 486,
              "loc": {
                "start": {
                  "line": 11,
                  "column": 32
                },
                "end": {
                  "line": 11,
                  "column": 34
                },
                "identifierName": "fn"
              },
              "name": "fn"
            }
          ],
          "body": {
            "type": "BlockStatement",
            "start": 491,
            "end": 769,
            "loc": {
              "start": {
                "line": 11,
                "column": 39
              },
              "end": {
                "line": 21,
                "column": 1
              }
            },
            "body": [
              {
                "type": "VariableDeclaration",
                "start": 497,
                "end": 509,
                "loc": {
                  "start": {
                    "line": 12,
                    "column": 4
                  },
                  "end": {
                    "line": 12,
                    "column": 16
                  }
                },
                "declarations": [
                  {
                    "type": "VariableDeclarator",
                    "start": 501,
                    "end": 508,
                    "loc": {
                      "start": {
                        "line": 12,
                        "column": 8
                      },
                      "end": {
                        "line": 12,
                        "column": 15
                      }
                    },
                    "id": {
                      "type": "Identifier",
                      "start": 501,
                      "end": 508,
                      "loc": {
                        "start": {
                          "line": 12,
                          "column": 8
                        },
                        "end": {
                          "line": 12,
                          "column": 15
                        },
                        "identifierName": "timeout"
                      },
                      "name": "timeout"
                    },
                    "init": null
                  }
                ],
                "kind": "let"
              },
              {
                "type": "FunctionDeclaration",
                "start": 514,
                "end": 709,
                "loc": {
                  "start": {
                    "line": 13,
                    "column": 4
                  },
                  "end": {
                    "line": 18,
                    "column": 5
                  }
                },
                "id": {
                  "type": "Identifier",
                  "start": 523,
                  "end": 524,
                  "loc": {
                    "start": {
                      "line": 13,
                      "column": 13
                    },
                    "end": {
                      "line": 13,
                      "column": 14
                    },
                    "identifierName": "f"
                  },
                  "name": "f"
                },
                "generator": false,
                "expression": false,
                "async": false,
                "params": [],
                "body": {
                  "type": "BlockStatement",
                  "start": 527,
                  "end": 709,
                  "loc": {
                    "start": {
                      "line": 13,
                      "column": 17
                    },
                    "end": {
                      "line": 18,
                      "column": 5
                    }
                  },
                  "body": [
                    {
                      "type": "VariableDeclaration",
                      "start": 537,
                      "end": 558,
                      "loc": {
                        "start": {
                          "line": 14,
                          "column": 8
                        },
                        "end": {
                          "line": 14,
                          "column": 29
                        }
                      },
                      "declarations": [
                        {
                          "type": "VariableDeclarator",
                          "start": 541,
                          "end": 557,
                          "loc": {
                            "start": {
                              "line": 14,
                              "column": 12
                            },
                            "end": {
                              "line": 14,
                              "column": 28
                            }
                          },
                          "id": {
                            "type": "Identifier",
                            "start": 541,
                            "end": 545,
                            "loc": {
                              "start": {
                                "line": 14,
                                "column": 12
                              },
                              "end": {
                                "line": 14,
                                "column": 16
                              },
                              "identifierName": "args"
                            },
                            "name": "args"
                          },
                          "init": {
                            "type": "Identifier",
                            "start": 548,
                            "end": 557,
                            "loc": {
                              "start": {
                                "line": 14,
                                "column": 19
                              },
                              "end": {
                                "line": 14,
                                "column": 28
                              },
                              "identifierName": "arguments"
                            },
                            "name": "arguments"
                          }
                        }
                      ],
                      "kind": "let"
                    },
                    {
                      "type": "ExpressionStatement",
                      "start": 567,
                      "end": 589,
                      "loc": {
                        "start": {
                          "line": 15,
                          "column": 8
                        },
                        "end": {
                          "line": 15,
                          "column": 30
                        }
                      },
                      "expression": {
                        "type": "CallExpression",
                        "start": 567,
                        "end": 588,
                        "loc": {
                          "start": {
                            "line": 15,
                            "column": 8
                          },
                          "end": {
                            "line": 15,
                            "column": 29
                          }
                        },
                        "callee": {
                          "type": "Identifier",
                          "start": 567,
                          "end": 579,
                          "loc": {
                            "start": {
                              "line": 15,
                              "column": 8
                            },
                            "end": {
                              "line": 15,
                              "column": 20
                            },
                            "identifierName": "clearTimeout"
                          },
                          "name": "clearTimeout"
                        },
                        "arguments": [
                          {
                            "type": "Identifier",
                            "start": 580,
                            "end": 587,
                            "loc": {
                              "start": {
                                "line": 15,
                                "column": 21
                              },
                              "end": {
                                "line": 15,
                                "column": 28
                              },
                              "identifierName": "timeout"
                            },
                            "name": "timeout"
                          }
                        ]
                      }
                    },
                    {
                      "type": "ExpressionStatement",
                      "start": 598,
                      "end": 703,
                      "loc": {
                        "start": {
                          "line": 16,
                          "column": 8
                        },
                        "end": {
                          "line": 17,
                          "column": 14
                        }
                      },
                      "expression": {
                        "type": "AssignmentExpression",
                        "start": 598,
                        "end": 702,
                        "loc": {
                          "start": {
                            "line": 16,
                            "column": 8
                          },
                          "end": {
                            "line": 17,
                            "column": 13
                          }
                        },
                        "operator": "=",
                        "left": {
                          "type": "Identifier",
                          "start": 598,
                          "end": 605,
                          "loc": {
                            "start": {
                              "line": 16,
                              "column": 8
                            },
                            "end": {
                              "line": 16,
                              "column": 15
                            },
                            "identifierName": "timeout"
                          },
                          "name": "timeout"
                        },
                        "right": {
                          "type": "CallExpression",
                          "start": 608,
                          "end": 702,
                          "loc": {
                            "start": {
                              "line": 16,
                              "column": 18
                            },
                            "end": {
                              "line": 17,
                              "column": 13
                            }
                          },
                          "callee": {
                            "type": "Identifier",
                            "start": 608,
                            "end": 618,
                            "loc": {
                              "start": {
                                "line": 16,
                                "column": 18
                              },
                              "end": {
                                "line": 16,
                                "column": 28
                              },
                              "identifierName": "setTimeout"
                            },
                            "name": "setTimeout"
                          },
                          "arguments": [
                            {
                              "type": "ArrowFunctionExpression",
                              "start": 619,
                              "end": 645,
                              "loc": {
                                "start": {
                                  "line": 16,
                                  "column": 29
                                },
                                "end": {
                                  "line": 16,
                                  "column": 55
                                }
                              },
                              "id": null,
                              "generator": false,
                              "expression": true,
                              "async": false,
                              "params": [],
                              "body": {
                                "type": "CallExpression",
                                "start": 625,
                                "end": 645,
                                "loc": {
                                  "start": {
                                    "line": 16,
                                    "column": 35
                                  },
                                  "end": {
                                    "line": 16,
                                    "column": 55
                                  }
                                },
                                "callee": {
                                  "type": "MemberExpression",
                                  "start": 625,
                                  "end": 633,
                                  "loc": {
                                    "start": {
                                      "line": 16,
                                      "column": 35
                                    },
                                    "end": {
                                      "line": 16,
                                      "column": 43
                                    }
                                  },
                                  "object": {
                                    "type": "Identifier",
                                    "start": 625,
                                    "end": 627,
                                    "loc": {
                                      "start": {
                                        "line": 16,
                                        "column": 35
                                      },
                                      "end": {
                                        "line": 16,
                                        "column": 37
                                      },
                                      "identifierName": "fn"
                                    },
                                    "name": "fn"
                                  },
                                  "property": {
                                    "type": "Identifier",
                                    "start": 628,
                                    "end": 633,
                                    "loc": {
                                      "start": {
                                        "line": 16,
                                        "column": 38
                                      },
                                      "end": {
                                        "line": 16,
                                        "column": 43
                                      },
                                      "identifierName": "apply"
                                    },
                                    "name": "apply"
                                  },
                                  "computed": false
                                },
                                "arguments": [
                                  {
                                    "type": "ThisExpression",
                                    "start": 634,
                                    "end": 638,
                                    "loc": {
                                      "start": {
                                        "line": 16,
                                        "column": 44
                                      },
                                      "end": {
                                        "line": 16,
                                        "column": 48
                                      }
                                    }
                                  },
                                  {
                                    "type": "Identifier",
                                    "start": 640,
                                    "end": 644,
                                    "loc": {
                                      "start": {
                                        "line": 16,
                                        "column": 50
                                      },
                                      "end": {
                                        "line": 16,
                                        "column": 54
                                      },
                                      "identifierName": "args"
                                    },
                                    "name": "args"
                                  }
                                ]
                              }
                            },
                            {
                              "type": "Identifier",
                              "start": 697,
                              "end": 701,
                              "loc": {
                                "start": {
                                  "line": 17,
                                  "column": 8
                                },
                                "end": {
                                  "line": 17,
                                  "column": 12
                                },
                                "identifierName": "wait"
                              },
                              "name": "wait",
                              "leadingComments": [
                                {
                                  "type": "CommentLine",
                                  "value": " eslint-disable-line prefer-rest-params",
                                  "start": 647,
                                  "end": 688,
                                  "loc": {
                                    "start": {
                                      "line": 16,
                                      "column": 57
                                    },
                                    "end": {
                                      "line": 16,
                                      "column": 98
                                    }
                                  }
                                }
                              ]
                            }
                          ]
                        }
                      }
                    }
                  ],
                  "directives": []
                }
              },
              {
                "type": "ExpressionStatement",
                "start": 714,
                "end": 753,
                "loc": {
                  "start": {
                    "line": 19,
                    "column": 4
                  },
                  "end": {
                    "line": 19,
                    "column": 43
                  }
                },
                "expression": {
                  "type": "AssignmentExpression",
                  "start": 714,
                  "end": 752,
                  "loc": {
                    "start": {
                      "line": 19,
                      "column": 4
                    },
                    "end": {
                      "line": 19,
                      "column": 42
                    }
                  },
                  "operator": "=",
                  "left": {
                    "type": "MemberExpression",
                    "start": 714,
                    "end": 722,
                    "loc": {
                      "start": {
                        "line": 19,
                        "column": 4
                      },
                      "end": {
                        "line": 19,
                        "column": 12
                      }
                    },
                    "object": {
                      "type": "Identifier",
                      "start": 714,
                      "end": 715,
                      "loc": {
                        "start": {
                          "line": 19,
                          "column": 4
                        },
                        "end": {
                          "line": 19,
                          "column": 5
                        },
                        "identifierName": "f"
                      },
                      "name": "f"
                    },
                    "property": {
                      "type": "Identifier",
                      "start": 716,
                      "end": 722,
                      "loc": {
                        "start": {
                          "line": 19,
                          "column": 6
                        },
                        "end": {
                          "line": 19,
                          "column": 12
                        },
                        "identifierName": "cancel"
                      },
                      "name": "cancel"
                    },
                    "computed": false
                  },
                  "right": {
                    "type": "ArrowFunctionExpression",
                    "start": 725,
                    "end": 752,
                    "loc": {
                      "start": {
                        "line": 19,
                        "column": 15
                      },
                      "end": {
                        "line": 19,
                        "column": 42
                      }
                    },
                    "id": null,
                    "generator": false,
                    "expression": true,
                    "async": false,
                    "params": [],
                    "body": {
                      "type": "CallExpression",
                      "start": 731,
                      "end": 752,
                      "loc": {
                        "start": {
                          "line": 19,
                          "column": 21
                        },
                        "end": {
                          "line": 19,
                          "column": 42
                        }
                      },
                      "callee": {
                        "type": "Identifier",
                        "start": 731,
                        "end": 743,
                        "loc": {
                          "start": {
                            "line": 19,
                            "column": 21
                          },
                          "end": {
                            "line": 19,
                            "column": 33
                          },
                          "identifierName": "clearTimeout"
                        },
                        "name": "clearTimeout"
                      },
                      "arguments": [
                        {
                          "type": "Identifier",
                          "start": 744,
                          "end": 751,
                          "loc": {
                            "start": {
                              "line": 19,
                              "column": 34
                            },
                            "end": {
                              "line": 19,
                              "column": 41
                            },
                            "identifierName": "timeout"
                          },
                          "name": "timeout"
                        }
                      ]
                    }
                  }
                }
              },
              {
                "type": "ReturnStatement",
                "start": 758,
                "end": 767,
                "loc": {
                  "start": {
                    "line": 20,
                    "column": 4
                  },
                  "end": {
                    "line": 20,
                    "column": 13
                  }
                },
                "argument": {
                  "type": "Identifier",
                  "start": 765,
                  "end": 766,
                  "loc": {
                    "start": {
                      "line": 20,
                      "column": 11
                    },
                    "end": {
                      "line": 20,
                      "column": 12
                    },
                    "identifierName": "f"
                  },
                  "name": "f"
                }
              }
            ],
            "directives": []
          },
          "_curryN": 2,
          "leadingComments": [
            {
              "type": "CommentBlock",
              "value": "*\n * Creates a debounced function that delays invoking `func` until after `wait`\n * milliseconds have elapsed since the last time the debounced function was\n * invoked. Delayed function invocation might be cancelled by calling cancel method.\n *\n * @param {number} wait The number of milliseconds to delay.\n * @param {Function} fn The function to debounce.\n * @returns {Function} Returns the new debounced function.\n ",
              "start": 31,
              "end": 451,
              "loc": {
                "start": {
                  "line": 2,
                  "column": 0
                },
                "end": {
                  "line": 10,
                  "column": 3
                }
              }
            }
          ],
          "trailingComments": []
        },
        "leadingComments": [
          {
            "type": "CommentBlock",
            "value": "*\n * Creates a debounced function that delays invoking `func` until after `wait`\n * milliseconds have elapsed since the last time the debounced function was\n * invoked. Delayed function invocation might be cancelled by calling cancel method.\n *\n * @param {number} wait The number of milliseconds to delay.\n * @param {Function} fn The function to debounce.\n * @returns {Function} Returns the new debounced function.\n ",
            "start": 31,
            "end": 451,
            "loc": {
              "start": {
                "line": 2,
                "column": 0
              },
              "end": {
                "line": 10,
                "column": 3
              }
            }
          }
        ]
      }
    ],
    "directives": []
  },
  "comments": [
    {
      "type": "CommentBlock",
      "value": "*\n * Creates a debounced function that delays invoking `func` until after `wait`\n * milliseconds have elapsed since the last time the debounced function was\n * invoked. Delayed function invocation might be cancelled by calling cancel method.\n *\n * @param {number} wait The number of milliseconds to delay.\n * @param {Function} fn The function to debounce.\n * @returns {Function} Returns the new debounced function.\n ",
      "start": 31,
      "end": 451,
      "loc": {
        "start": {
          "line": 2,
          "column": 0
        },
        "end": {
          "line": 10,
          "column": 3
        }
      }
    },
    {
      "type": "CommentLine",
      "value": " eslint-disable-line prefer-rest-params",
      "start": 647,
      "end": 688,
      "loc": {
        "start": {
          "line": 16,
          "column": 57
        },
        "end": {
          "line": 16,
          "column": 98
        }
      }
    }
  ],
  "tokens": [
    {
      "type": {
        "label": "import",
        "keyword": "import",
        "beforeExpr": false,
        "startsExpr": true,
        "rightAssociative": false,
        "isLoop": false,
        "isAssign": false,
        "prefix": false,
        "postfix": false,
        "binop": null,
        "updateContext": null
      },
      "value": "import",
      "start": 0,
      "end": 6,
      "loc": {
        "start": {
          "line": 1,
          "column": 0
        },
        "end": {
          "line": 1,
          "column": 6
        }
      }
    },
    {
      "type": {
        "label": "name",
        "beforeExpr": false,
        "startsExpr": true,
        "rightAssociative": false,
        "isLoop": false,
        "isAssign": false,
        "prefix": false,
        "postfix": false,
        "binop": null
      },
      "value": "curryN",
      "start": 7,
      "end": 13,
      "loc": {
        "start": {
          "line": 1,
          "column": 7
        },
        "end": {
          "line": 1,
          "column": 13
        }
      }
    },
    {
      "type": {
        "label": "name",
        "beforeExpr": false,
        "startsExpr": true,
        "rightAssociative": false,
        "isLoop": false,
        "isAssign": false,
        "prefix": false,
        "postfix": false,
        "binop": null
      },
      "value": "from",
      "start": 14,
      "end": 18,
      "loc": {
        "start": {
          "line": 1,
          "column": 14
        },
        "end": {
          "line": 1,
          "column": 18
        }
      }
    },
    {
      "type": {
        "label": "string",
        "beforeExpr": false,
        "startsExpr": true,
        "rightAssociative": false,
        "isLoop": false,
        "isAssign": false,
        "prefix": false,
        "postfix": false,
        "binop": null,
        "updateContext": null
      },
      "value": "./curryN",
      "start": 19,
      "end": 29,
      "loc": {
        "start": {
          "line": 1,
          "column": 19
        },
        "end": {
          "line": 1,
          "column": 29
        }
      }
    },
    {
      "type": {
        "label": ";",
        "beforeExpr": true,
        "startsExpr": false,
        "rightAssociative": false,
        "isLoop": false,
        "isAssign": false,
        "prefix": false,
        "postfix": false,
        "binop": null,
        "updateContext": null
      },
      "start": 29,
      "end": 30,
      "loc": {
        "start": {
          "line": 1,
          "column": 29
        },
        "end": {
          "line": 1,
          "column": 30
        }
      }
    },
    {
      "type": "CommentBlock",
      "value": "*\n * Creates a debounced function that delays invoking `func` until after `wait`\n * milliseconds have elapsed since the last time the debounced function was\n * invoked. Delayed function invocation might be cancelled by calling cancel method.\n *\n * @param {number} wait The number of milliseconds to delay.\n * @param {Function} fn The function to debounce.\n * @returns {Function} Returns the new debounced function.\n ",
      "start": 31,
      "end": 451,
      "loc": {
        "start": {
          "line": 2,
          "column": 0
        },
        "end": {
          "line": 10,
          "column": 3
        }
      }
    },
    {
      "type": {
        "label": "export",
        "keyword": "export",
        "beforeExpr": false,
        "startsExpr": false,
        "rightAssociative": false,
        "isLoop": false,
        "isAssign": false,
        "prefix": false,
        "postfix": false,
        "binop": null,
        "updateContext": null
      },
      "value": "export",
      "start": 452,
      "end": 458,
      "loc": {
        "start": {
          "line": 11,
          "column": 0
        },
        "end": {
          "line": 11,
          "column": 6
        }
      }
    },
    {
      "type": {
        "label": "default",
        "keyword": "default",
        "beforeExpr": true,
        "startsExpr": false,
        "rightAssociative": false,
        "isLoop": false,
        "isAssign": false,
        "prefix": false,
        "postfix": false,
        "binop": null,
        "updateContext": null
      },
      "value": "default",
      "start": 459,
      "end": 466,
      "loc": {
        "start": {
          "line": 11,
          "column": 7
        },
        "end": {
          "line": 11,
          "column": 14
        }
      }
    },
    {
      "type": {
        "label": "name",
        "beforeExpr": false,
        "startsExpr": true,
        "rightAssociative": false,
        "isLoop": false,
        "isAssign": false,
        "prefix": false,
        "postfix": false,
        "binop": null
      },
      "value": "curryN",
      "start": 467,
      "end": 473,
      "loc": {
        "start": {
          "line": 11,
          "column": 15
        },
        "end": {
          "line": 11,
          "column": 21
        }
      }
    },
    {
      "type": {
        "label": "(",
        "beforeExpr": true,
        "startsExpr": true,
        "rightAssociative": false,
        "isLoop": false,
        "isAssign": false,
        "prefix": false,
        "postfix": false,
        "binop": null
      },
      "start": 473,
      "end": 474,
      "loc": {
        "start": {
          "line": 11,
          "column": 21
        },
        "end": {
          "line": 11,
          "column": 22
        }
      }
    },
    {
      "type": {
        "label": "num",
        "beforeExpr": false,
        "startsExpr": true,
        "rightAssociative": false,
        "isLoop": false,
        "isAssign": false,
        "prefix": false,
        "postfix": false,
        "binop": null,
        "updateContext": null
      },
      "value": 2,
      "start": 474,
      "end": 475,
      "loc": {
        "start": {
          "line": 11,
          "column": 22
        },
        "end": {
          "line": 11,
          "column": 23
        }
      }
    },
    {
      "type": {
        "label": ",",
        "beforeExpr": true,
        "startsExpr": false,
        "rightAssociative": false,
        "isLoop": false,
        "isAssign": false,
        "prefix": false,
        "postfix": false,
        "binop": null,
        "updateContext": null
      },
      "start": 475,
      "end": 476,
      "loc": {
        "start": {
          "line": 11,
          "column": 23
        },
        "end": {
          "line": 11,
          "column": 24
        }
      }
    },
    {
      "type": {
        "label": "(",
        "beforeExpr": true,
        "startsExpr": true,
        "rightAssociative": false,
        "isLoop": false,
        "isAssign": false,
        "prefix": false,
        "postfix": false,
        "binop": null
      },
      "start": 477,
      "end": 478,
      "loc": {
        "start": {
          "line": 11,
          "column": 25
        },
        "end": {
          "line": 11,
          "column": 26
        }
      }
    },
    {
      "type": {
        "label": "name",
        "beforeExpr": false,
        "startsExpr": true,
        "rightAssociative": false,
        "isLoop": false,
        "isAssign": false,
        "prefix": false,
        "postfix": false,
        "binop": null
      },
      "value": "wait",
      "start": 478,
      "end": 482,
      "loc": {
        "start": {
          "line": 11,
          "column": 26
        },
        "end": {
          "line": 11,
          "column": 30
        }
      }
    },
    {
      "type": {
        "label": ",",
        "beforeExpr": true,
        "startsExpr": false,
        "rightAssociative": false,
        "isLoop": false,
        "isAssign": false,
        "prefix": false,
        "postfix": false,
        "binop": null,
        "updateContext": null
      },
      "start": 482,
      "end": 483,
      "loc": {
        "start": {
          "line": 11,
          "column": 30
        },
        "end": {
          "line": 11,
          "column": 31
        }
      }
    },
    {
      "type": {
        "label": "name",
        "beforeExpr": false,
        "startsExpr": true,
        "rightAssociative": false,
        "isLoop": false,
        "isAssign": false,
        "prefix": false,
        "postfix": false,
        "binop": null
      },
      "value": "fn",
      "start": 484,
      "end": 486,
      "loc": {
        "start": {
          "line": 11,
          "column": 32
        },
        "end": {
          "line": 11,
          "column": 34
        }
      }
    },
    {
      "type": {
        "label": ")",
        "beforeExpr": false,
        "startsExpr": false,
        "rightAssociative": false,
        "isLoop": false,
        "isAssign": false,
        "prefix": false,
        "postfix": false,
        "binop": null
      },
      "start": 486,
      "end": 487,
      "loc": {
        "start": {
          "line": 11,
          "column": 34
        },
        "end": {
          "line": 11,
          "column": 35
        }
      }
    },
    {
      "type": {
        "label": "=>",
        "beforeExpr": true,
        "startsExpr": false,
        "rightAssociative": false,
        "isLoop": false,
        "isAssign": false,
        "prefix": false,
        "postfix": false,
        "binop": null,
        "updateContext": null
      },
      "start": 488,
      "end": 490,
      "loc": {
        "start": {
          "line": 11,
          "column": 36
        },
        "end": {
          "line": 11,
          "column": 38
        }
      }
    },
    {
      "type": {
        "label": "{",
        "beforeExpr": true,
        "startsExpr": true,
        "rightAssociative": false,
        "isLoop": false,
        "isAssign": false,
        "prefix": false,
        "postfix": false,
        "binop": null
      },
      "start": 491,
      "end": 492,
      "loc": {
        "start": {
          "line": 11,
          "column": 39
        },
        "end": {
          "line": 11,
          "column": 40
        }
      }
    },
    {
      "type": {
        "label": "let",
        "keyword": "let",
        "beforeExpr": false,
        "startsExpr": false,
        "rightAssociative": false,
        "isLoop": false,
        "isAssign": false,
        "prefix": false,
        "postfix": false,
        "binop": null,
        "updateContext": null
      },
      "value": "let",
      "start": 497,
      "end": 500,
      "loc": {
        "start": {
          "line": 12,
          "column": 4
        },
        "end": {
          "line": 12,
          "column": 7
        }
      }
    },
    {
      "type": {
        "label": "name",
        "beforeExpr": false,
        "startsExpr": true,
        "rightAssociative": false,
        "isLoop": false,
        "isAssign": false,
        "prefix": false,
        "postfix": false,
        "binop": null
      },
      "value": "timeout",
      "start": 501,
      "end": 508,
      "loc": {
        "start": {
          "line": 12,
          "column": 8
        },
        "end": {
          "line": 12,
          "column": 15
        }
      }
    },
    {
      "type": {
        "label": ";",
        "beforeExpr": true,
        "startsExpr": false,
        "rightAssociative": false,
        "isLoop": false,
        "isAssign": false,
        "prefix": false,
        "postfix": false,
        "binop": null,
        "updateContext": null
      },
      "start": 508,
      "end": 509,
      "loc": {
        "start": {
          "line": 12,
          "column": 15
        },
        "end": {
          "line": 12,
          "column": 16
        }
      }
    },
    {
      "type": {
        "label": "function",
        "keyword": "function",
        "beforeExpr": false,
        "startsExpr": true,
        "rightAssociative": false,
        "isLoop": false,
        "isAssign": false,
        "prefix": false,
        "postfix": false,
        "binop": null
      },
      "value": "function",
      "start": 514,
      "end": 522,
      "loc": {
        "start": {
          "line": 13,
          "column": 4
        },
        "end": {
          "line": 13,
          "column": 12
        }
      }
    },
    {
      "type": {
        "label": "name",
        "beforeExpr": false,
        "startsExpr": true,
        "rightAssociative": false,
        "isLoop": false,
        "isAssign": false,
        "prefix": false,
        "postfix": false,
        "binop": null
      },
      "value": "f",
      "start": 523,
      "end": 524,
      "loc": {
        "start": {
          "line": 13,
          "column": 13
        },
        "end": {
          "line": 13,
          "column": 14
        }
      }
    },
    {
      "type": {
        "label": "(",
        "beforeExpr": true,
        "startsExpr": true,
        "rightAssociative": false,
        "isLoop": false,
        "isAssign": false,
        "prefix": false,
        "postfix": false,
        "binop": null
      },
      "start": 524,
      "end": 525,
      "loc": {
        "start": {
          "line": 13,
          "column": 14
        },
        "end": {
          "line": 13,
          "column": 15
        }
      }
    },
    {
      "type": {
        "label": ")",
        "beforeExpr": false,
        "startsExpr": false,
        "rightAssociative": false,
        "isLoop": false,
        "isAssign": false,
        "prefix": false,
        "postfix": false,
        "binop": null
      },
      "start": 525,
      "end": 526,
      "loc": {
        "start": {
          "line": 13,
          "column": 15
        },
        "end": {
          "line": 13,
          "column": 16
        }
      }
    },
    {
      "type": {
        "label": "{",
        "beforeExpr": true,
        "startsExpr": true,
        "rightAssociative": false,
        "isLoop": false,
        "isAssign": false,
        "prefix": false,
        "postfix": false,
        "binop": null
      },
      "start": 527,
      "end": 528,
      "loc": {
        "start": {
          "line": 13,
          "column": 17
        },
        "end": {
          "line": 13,
          "column": 18
        }
      }
    },
    {
      "type": {
        "label": "let",
        "keyword": "let",
        "beforeExpr": false,
        "startsExpr": false,
        "rightAssociative": false,
        "isLoop": false,
        "isAssign": false,
        "prefix": false,
        "postfix": false,
        "binop": null,
        "updateContext": null
      },
      "value": "let",
      "start": 537,
      "end": 540,
      "loc": {
        "start": {
          "line": 14,
          "column": 8
        },
        "end": {
          "line": 14,
          "column": 11
        }
      }
    },
    {
      "type": {
        "label": "name",
        "beforeExpr": false,
        "startsExpr": true,
        "rightAssociative": false,
        "isLoop": false,
        "isAssign": false,
        "prefix": false,
        "postfix": false,
        "binop": null
      },
      "value": "args",
      "start": 541,
      "end": 545,
      "loc": {
        "start": {
          "line": 14,
          "column": 12
        },
        "end": {
          "line": 14,
          "column": 16
        }
      }
    },
    {
      "type": {
        "label": "=",
        "beforeExpr": true,
        "startsExpr": false,
        "rightAssociative": false,
        "isLoop": false,
        "isAssign": true,
        "prefix": false,
        "postfix": false,
        "binop": null,
        "updateContext": null
      },
      "value": "=",
      "start": 546,
      "end": 547,
      "loc": {
        "start": {
          "line": 14,
          "column": 17
        },
        "end": {
          "line": 14,
          "column": 18
        }
      }
    },
    {
      "type": {
        "label": "name",
        "beforeExpr": false,
        "startsExpr": true,
        "rightAssociative": false,
        "isLoop": false,
        "isAssign": false,
        "prefix": false,
        "postfix": false,
        "binop": null
      },
      "value": "arguments",
      "start": 548,
      "end": 557,
      "loc": {
        "start": {
          "line": 14,
          "column": 19
        },
        "end": {
          "line": 14,
          "column": 28
        }
      }
    },
    {
      "type": {
        "label": ";",
        "beforeExpr": true,
        "startsExpr": false,
        "rightAssociative": false,
        "isLoop": false,
        "isAssign": false,
        "prefix": false,
        "postfix": false,
        "binop": null,
        "updateContext": null
      },
      "start": 557,
      "end": 558,
      "loc": {
        "start": {
          "line": 14,
          "column": 28
        },
        "end": {
          "line": 14,
          "column": 29
        }
      }
    },
    {
      "type": {
        "label": "name",
        "beforeExpr": false,
        "startsExpr": true,
        "rightAssociative": false,
        "isLoop": false,
        "isAssign": false,
        "prefix": false,
        "postfix": false,
        "binop": null
      },
      "value": "clearTimeout",
      "start": 567,
      "end": 579,
      "loc": {
        "start": {
          "line": 15,
          "column": 8
        },
        "end": {
          "line": 15,
          "column": 20
        }
      }
    },
    {
      "type": {
        "label": "(",
        "beforeExpr": true,
        "startsExpr": true,
        "rightAssociative": false,
        "isLoop": false,
        "isAssign": false,
        "prefix": false,
        "postfix": false,
        "binop": null
      },
      "start": 579,
      "end": 580,
      "loc": {
        "start": {
          "line": 15,
          "column": 20
        },
        "end": {
          "line": 15,
          "column": 21
        }
      }
    },
    {
      "type": {
        "label": "name",
        "beforeExpr": false,
        "startsExpr": true,
        "rightAssociative": false,
        "isLoop": false,
        "isAssign": false,
        "prefix": false,
        "postfix": false,
        "binop": null
      },
      "value": "timeout",
      "start": 580,
      "end": 587,
      "loc": {
        "start": {
          "line": 15,
          "column": 21
        },
        "end": {
          "line": 15,
          "column": 28
        }
      }
    },
    {
      "type": {
        "label": ")",
        "beforeExpr": false,
        "startsExpr": false,
        "rightAssociative": false,
        "isLoop": false,
        "isAssign": false,
        "prefix": false,
        "postfix": false,
        "binop": null
      },
      "start": 587,
      "end": 588,
      "loc": {
        "start": {
          "line": 15,
          "column": 28
        },
        "end": {
          "line": 15,
          "column": 29
        }
      }
    },
    {
      "type": {
        "label": ";",
        "beforeExpr": true,
        "startsExpr": false,
        "rightAssociative": false,
        "isLoop": false,
        "isAssign": false,
        "prefix": false,
        "postfix": false,
        "binop": null,
        "updateContext": null
      },
      "start": 588,
      "end": 589,
      "loc": {
        "start": {
          "line": 15,
          "column": 29
        },
        "end": {
          "line": 15,
          "column": 30
        }
      }
    },
    {
      "type": {
        "label": "name",
        "beforeExpr": false,
        "startsExpr": true,
        "rightAssociative": false,
        "isLoop": false,
        "isAssign": false,
        "prefix": false,
        "postfix": false,
        "binop": null
      },
      "value": "timeout",
      "start": 598,
      "end": 605,
      "loc": {
        "start": {
          "line": 16,
          "column": 8
        },
        "end": {
          "line": 16,
          "column": 15
        }
      }
    },
    {
      "type": {
        "label": "=",
        "beforeExpr": true,
        "startsExpr": false,
        "rightAssociative": false,
        "isLoop": false,
        "isAssign": true,
        "prefix": false,
        "postfix": false,
        "binop": null,
        "updateContext": null
      },
      "value": "=",
      "start": 606,
      "end": 607,
      "loc": {
        "start": {
          "line": 16,
          "column": 16
        },
        "end": {
          "line": 16,
          "column": 17
        }
      }
    },
    {
      "type": {
        "label": "name",
        "beforeExpr": false,
        "startsExpr": true,
        "rightAssociative": false,
        "isLoop": false,
        "isAssign": false,
        "prefix": false,
        "postfix": false,
        "binop": null
      },
      "value": "setTimeout",
      "start": 608,
      "end": 618,
      "loc": {
        "start": {
          "line": 16,
          "column": 18
        },
        "end": {
          "line": 16,
          "column": 28
        }
      }
    },
    {
      "type": {
        "label": "(",
        "beforeExpr": true,
        "startsExpr": true,
        "rightAssociative": false,
        "isLoop": false,
        "isAssign": false,
        "prefix": false,
        "postfix": false,
        "binop": null
      },
      "start": 618,
      "end": 619,
      "loc": {
        "start": {
          "line": 16,
          "column": 28
        },
        "end": {
          "line": 16,
          "column": 29
        }
      }
    },
    {
      "type": {
        "label": "(",
        "beforeExpr": true,
        "startsExpr": true,
        "rightAssociative": false,
        "isLoop": false,
        "isAssign": false,
        "prefix": false,
        "postfix": false,
        "binop": null
      },
      "start": 619,
      "end": 620,
      "loc": {
        "start": {
          "line": 16,
          "column": 29
        },
        "end": {
          "line": 16,
          "column": 30
        }
      }
    },
    {
      "type": {
        "label": ")",
        "beforeExpr": false,
        "startsExpr": false,
        "rightAssociative": false,
        "isLoop": false,
        "isAssign": false,
        "prefix": false,
        "postfix": false,
        "binop": null
      },
      "start": 620,
      "end": 621,
      "loc": {
        "start": {
          "line": 16,
          "column": 30
        },
        "end": {
          "line": 16,
          "column": 31
        }
      }
    },
    {
      "type": {
        "label": "=>",
        "beforeExpr": true,
        "startsExpr": false,
        "rightAssociative": false,
        "isLoop": false,
        "isAssign": false,
        "prefix": false,
        "postfix": false,
        "binop": null,
        "updateContext": null
      },
      "start": 622,
      "end": 624,
      "loc": {
        "start": {
          "line": 16,
          "column": 32
        },
        "end": {
          "line": 16,
          "column": 34
        }
      }
    },
    {
      "type": {
        "label": "name",
        "beforeExpr": false,
        "startsExpr": true,
        "rightAssociative": false,
        "isLoop": false,
        "isAssign": false,
        "prefix": false,
        "postfix": false,
        "binop": null
      },
      "value": "fn",
      "start": 625,
      "end": 627,
      "loc": {
        "start": {
          "line": 16,
          "column": 35
        },
        "end": {
          "line": 16,
          "column": 37
        }
      }
    },
    {
      "type": {
        "label": ".",
        "beforeExpr": false,
        "startsExpr": false,
        "rightAssociative": false,
        "isLoop": false,
        "isAssign": false,
        "prefix": false,
        "postfix": false,
        "binop": null,
        "updateContext": null
      },
      "start": 627,
      "end": 628,
      "loc": {
        "start": {
          "line": 16,
          "column": 37
        },
        "end": {
          "line": 16,
          "column": 38
        }
      }
    },
    {
      "type": {
        "label": "name",
        "beforeExpr": false,
        "startsExpr": true,
        "rightAssociative": false,
        "isLoop": false,
        "isAssign": false,
        "prefix": false,
        "postfix": false,
        "binop": null
      },
      "value": "apply",
      "start": 628,
      "end": 633,
      "loc": {
        "start": {
          "line": 16,
          "column": 38
        },
        "end": {
          "line": 16,
          "column": 43
        }
      }
    },
    {
      "type": {
        "label": "(",
        "beforeExpr": true,
        "startsExpr": true,
        "rightAssociative": false,
        "isLoop": false,
        "isAssign": false,
        "prefix": false,
        "postfix": false,
        "binop": null
      },
      "start": 633,
      "end": 634,
      "loc": {
        "start": {
          "line": 16,
          "column": 43
        },
        "end": {
          "line": 16,
          "column": 44
        }
      }
    },
    {
      "type": {
        "label": "this",
        "keyword": "this",
        "beforeExpr": false,
        "startsExpr": true,
        "rightAssociative": false,
        "isLoop": false,
        "isAssign": false,
        "prefix": false,
        "postfix": false,
        "binop": null,
        "updateContext": null
      },
      "value": "this",
      "start": 634,
      "end": 638,
      "loc": {
        "start": {
          "line": 16,
          "column": 44
        },
        "end": {
          "line": 16,
          "column": 48
        }
      }
    },
    {
      "type": {
        "label": ",",
        "beforeExpr": true,
        "startsExpr": false,
        "rightAssociative": false,
        "isLoop": false,
        "isAssign": false,
        "prefix": false,
        "postfix": false,
        "binop": null,
        "updateContext": null
      },
      "start": 638,
      "end": 639,
      "loc": {
        "start": {
          "line": 16,
          "column": 48
        },
        "end": {
          "line": 16,
          "column": 49
        }
      }
    },
    {
      "type": {
        "label": "name",
        "beforeExpr": false,
        "startsExpr": true,
        "rightAssociative": false,
        "isLoop": false,
        "isAssign": false,
        "prefix": false,
        "postfix": false,
        "binop": null
      },
      "value": "args",
      "start": 640,
      "end": 644,
      "loc": {
        "start": {
          "line": 16,
          "column": 50
        },
        "end": {
          "line": 16,
          "column": 54
        }
      }
    },
    {
      "type": {
        "label": ")",
        "beforeExpr": false,
        "startsExpr": false,
        "rightAssociative": false,
        "isLoop": false,
        "isAssign": false,
        "prefix": false,
        "postfix": false,
        "binop": null
      },
      "start": 644,
      "end": 645,
      "loc": {
        "start": {
          "line": 16,
          "column": 54
        },
        "end": {
          "line": 16,
          "column": 55
        }
      }
    },
    {
      "type": {
        "label": ",",
        "beforeExpr": true,
        "startsExpr": false,
        "rightAssociative": false,
        "isLoop": false,
        "isAssign": false,
        "prefix": false,
        "postfix": false,
        "binop": null,
        "updateContext": null
      },
      "start": 645,
      "end": 646,
      "loc": {
        "start": {
          "line": 16,
          "column": 55
        },
        "end": {
          "line": 16,
          "column": 56
        }
      }
    },
    {
      "type": "CommentLine",
      "value": " eslint-disable-line prefer-rest-params",
      "start": 647,
      "end": 688,
      "loc": {
        "start": {
          "line": 16,
          "column": 57
        },
        "end": {
          "line": 16,
          "column": 98
        }
      }
    },
    {
      "type": {
        "label": "name",
        "beforeExpr": false,
        "startsExpr": true,
        "rightAssociative": false,
        "isLoop": false,
        "isAssign": false,
        "prefix": false,
        "postfix": false,
        "binop": null
      },
      "value": "wait",
      "start": 697,
      "end": 701,
      "loc": {
        "start": {
          "line": 17,
          "column": 8
        },
        "end": {
          "line": 17,
          "column": 12
        }
      }
    },
    {
      "type": {
        "label": ")",
        "beforeExpr": false,
        "startsExpr": false,
        "rightAssociative": false,
        "isLoop": false,
        "isAssign": false,
        "prefix": false,
        "postfix": false,
        "binop": null
      },
      "start": 701,
      "end": 702,
      "loc": {
        "start": {
          "line": 17,
          "column": 12
        },
        "end": {
          "line": 17,
          "column": 13
        }
      }
    },
    {
      "type": {
        "label": ";",
        "beforeExpr": true,
        "startsExpr": false,
        "rightAssociative": false,
        "isLoop": false,
        "isAssign": false,
        "prefix": false,
        "postfix": false,
        "binop": null,
        "updateContext": null
      },
      "start": 702,
      "end": 703,
      "loc": {
        "start": {
          "line": 17,
          "column": 13
        },
        "end": {
          "line": 17,
          "column": 14
        }
      }
    },
    {
      "type": {
        "label": "}",
        "beforeExpr": false,
        "startsExpr": false,
        "rightAssociative": false,
        "isLoop": false,
        "isAssign": false,
        "prefix": false,
        "postfix": false,
        "binop": null
      },
      "start": 708,
      "end": 709,
      "loc": {
        "start": {
          "line": 18,
          "column": 4
        },
        "end": {
          "line": 18,
          "column": 5
        }
      }
    },
    {
      "type": {
        "label": "name",
        "beforeExpr": false,
        "startsExpr": true,
        "rightAssociative": false,
        "isLoop": false,
        "isAssign": false,
        "prefix": false,
        "postfix": false,
        "binop": null
      },
      "value": "f",
      "start": 714,
      "end": 715,
      "loc": {
        "start": {
          "line": 19,
          "column": 4
        },
        "end": {
          "line": 19,
          "column": 5
        }
      }
    },
    {
      "type": {
        "label": ".",
        "beforeExpr": false,
        "startsExpr": false,
        "rightAssociative": false,
        "isLoop": false,
        "isAssign": false,
        "prefix": false,
        "postfix": false,
        "binop": null,
        "updateContext": null
      },
      "start": 715,
      "end": 716,
      "loc": {
        "start": {
          "line": 19,
          "column": 5
        },
        "end": {
          "line": 19,
          "column": 6
        }
      }
    },
    {
      "type": {
        "label": "name",
        "beforeExpr": false,
        "startsExpr": true,
        "rightAssociative": false,
        "isLoop": false,
        "isAssign": false,
        "prefix": false,
        "postfix": false,
        "binop": null
      },
      "value": "cancel",
      "start": 716,
      "end": 722,
      "loc": {
        "start": {
          "line": 19,
          "column": 6
        },
        "end": {
          "line": 19,
          "column": 12
        }
      }
    },
    {
      "type": {
        "label": "=",
        "beforeExpr": true,
        "startsExpr": false,
        "rightAssociative": false,
        "isLoop": false,
        "isAssign": true,
        "prefix": false,
        "postfix": false,
        "binop": null,
        "updateContext": null
      },
      "value": "=",
      "start": 723,
      "end": 724,
      "loc": {
        "start": {
          "line": 19,
          "column": 13
        },
        "end": {
          "line": 19,
          "column": 14
        }
      }
    },
    {
      "type": {
        "label": "(",
        "beforeExpr": true,
        "startsExpr": true,
        "rightAssociative": false,
        "isLoop": false,
        "isAssign": false,
        "prefix": false,
        "postfix": false,
        "binop": null
      },
      "start": 725,
      "end": 726,
      "loc": {
        "start": {
          "line": 19,
          "column": 15
        },
        "end": {
          "line": 19,
          "column": 16
        }
      }
    },
    {
      "type": {
        "label": ")",
        "beforeExpr": false,
        "startsExpr": false,
        "rightAssociative": false,
        "isLoop": false,
        "isAssign": false,
        "prefix": false,
        "postfix": false,
        "binop": null
      },
      "start": 726,
      "end": 727,
      "loc": {
        "start": {
          "line": 19,
          "column": 16
        },
        "end": {
          "line": 19,
          "column": 17
        }
      }
    },
    {
      "type": {
        "label": "=>",
        "beforeExpr": true,
        "startsExpr": false,
        "rightAssociative": false,
        "isLoop": false,
        "isAssign": false,
        "prefix": false,
        "postfix": false,
        "binop": null,
        "updateContext": null
      },
      "start": 728,
      "end": 730,
      "loc": {
        "start": {
          "line": 19,
          "column": 18
        },
        "end": {
          "line": 19,
          "column": 20
        }
      }
    },
    {
      "type": {
        "label": "name",
        "beforeExpr": false,
        "startsExpr": true,
        "rightAssociative": false,
        "isLoop": false,
        "isAssign": false,
        "prefix": false,
        "postfix": false,
        "binop": null
      },
      "value": "clearTimeout",
      "start": 731,
      "end": 743,
      "loc": {
        "start": {
          "line": 19,
          "column": 21
        },
        "end": {
          "line": 19,
          "column": 33
        }
      }
    },
    {
      "type": {
        "label": "(",
        "beforeExpr": true,
        "startsExpr": true,
        "rightAssociative": false,
        "isLoop": false,
        "isAssign": false,
        "prefix": false,
        "postfix": false,
        "binop": null
      },
      "start": 743,
      "end": 744,
      "loc": {
        "start": {
          "line": 19,
          "column": 33
        },
        "end": {
          "line": 19,
          "column": 34
        }
      }
    },
    {
      "type": {
        "label": "name",
        "beforeExpr": false,
        "startsExpr": true,
        "rightAssociative": false,
        "isLoop": false,
        "isAssign": false,
        "prefix": false,
        "postfix": false,
        "binop": null
      },
      "value": "timeout",
      "start": 744,
      "end": 751,
      "loc": {
        "start": {
          "line": 19,
          "column": 34
        },
        "end": {
          "line": 19,
          "column": 41
        }
      }
    },
    {
      "type": {
        "label": ")",
        "beforeExpr": false,
        "startsExpr": false,
        "rightAssociative": false,
        "isLoop": false,
        "isAssign": false,
        "prefix": false,
        "postfix": false,
        "binop": null
      },
      "start": 751,
      "end": 752,
      "loc": {
        "start": {
          "line": 19,
          "column": 41
        },
        "end": {
          "line": 19,
          "column": 42
        }
      }
    },
    {
      "type": {
        "label": ";",
        "beforeExpr": true,
        "startsExpr": false,
        "rightAssociative": false,
        "isLoop": false,
        "isAssign": false,
        "prefix": false,
        "postfix": false,
        "binop": null,
        "updateContext": null
      },
      "start": 752,
      "end": 753,
      "loc": {
        "start": {
          "line": 19,
          "column": 42
        },
        "end": {
          "line": 19,
          "column": 43
        }
      }
    },
    {
      "type": {
        "label": "return",
        "keyword": "return",
        "beforeExpr": true,
        "startsExpr": false,
        "rightAssociative": false,
        "isLoop": false,
        "isAssign": false,
        "prefix": false,
        "postfix": false,
        "binop": null,
        "updateContext": null
      },
      "value": "return",
      "start": 758,
      "end": 764,
      "loc": {
        "start": {
          "line": 20,
          "column": 4
        },
        "end": {
          "line": 20,
          "column": 10
        }
      }
    },
    {
      "type": {
        "label": "name",
        "beforeExpr": false,
        "startsExpr": true,
        "rightAssociative": false,
        "isLoop": false,
        "isAssign": false,
        "prefix": false,
        "postfix": false,
        "binop": null
      },
      "value": "f",
      "start": 765,
      "end": 766,
      "loc": {
        "start": {
          "line": 20,
          "column": 11
        },
        "end": {
          "line": 20,
          "column": 12
        }
      }
    },
    {
      "type": {
        "label": ";",
        "beforeExpr": true,
        "startsExpr": false,
        "rightAssociative": false,
        "isLoop": false,
        "isAssign": false,
        "prefix": false,
        "postfix": false,
        "binop": null,
        "updateContext": null
      },
      "start": 766,
      "end": 767,
      "loc": {
        "start": {
          "line": 20,
          "column": 12
        },
        "end": {
          "line": 20,
          "column": 13
        }
      }
    },
    {
      "type": {
        "label": "}",
        "beforeExpr": false,
        "startsExpr": false,
        "rightAssociative": false,
        "isLoop": false,
        "isAssign": false,
        "prefix": false,
        "postfix": false,
        "binop": null
      },
      "start": 768,
      "end": 769,
      "loc": {
        "start": {
          "line": 21,
          "column": 0
        },
        "end": {
          "line": 21,
          "column": 1
        }
      }
    },
    {
      "type": {
        "label": ")",
        "beforeExpr": false,
        "startsExpr": false,
        "rightAssociative": false,
        "isLoop": false,
        "isAssign": false,
        "prefix": false,
        "postfix": false,
        "binop": null
      },
      "start": 769,
      "end": 770,
      "loc": {
        "start": {
          "line": 21,
          "column": 1
        },
        "end": {
          "line": 21,
          "column": 2
        }
      }
    },
    {
      "type": {
        "label": ";",
        "beforeExpr": true,
        "startsExpr": false,
        "rightAssociative": false,
        "isLoop": false,
        "isAssign": false,
        "prefix": false,
        "postfix": false,
        "binop": null,
        "updateContext": null
      },
      "start": 770,
      "end": 771,
      "loc": {
        "start": {
          "line": 21,
          "column": 2
        },
        "end": {
          "line": 21,
          "column": 3
        }
      }
    },
    {
      "type": {
        "label": "eof",
        "beforeExpr": false,
        "startsExpr": false,
        "rightAssociative": false,
        "isLoop": false,
        "isAssign": false,
        "prefix": false,
        "postfix": false,
        "binop": null,
        "updateContext": null
      },
      "start": 772,
      "end": 772,
      "loc": {
        "start": {
          "line": 22,
          "column": 0
        },
        "end": {
          "line": 22,
          "column": 0
        }
      }
    }
  ]
}