{
  "type": "File",
  "start": 0,
  "end": 331,
  "loc": {
    "start": {
      "line": 1,
      "column": 0
    },
    "end": {
      "line": 15,
      "column": 0
    }
  },
  "program": {
    "type": "Program",
    "start": 0,
    "end": 331,
    "loc": {
      "start": {
        "line": 1,
        "column": 0
      },
      "end": {
        "line": 15,
        "column": 0
      }
    },
    "sourceType": "module",
    "body": [
      {
        "type": "ExportDefaultDeclaration",
        "start": 274,
        "end": 329,
        "loc": {
          "start": {
            "line": 14,
            "column": 0
          },
          "end": {
            "line": 14,
            "column": 55
          }
        },
        "declaration": {
          "type": "ArrowFunctionExpression",
          "start": 289,
          "end": 328,
          "loc": {
            "start": {
              "line": 14,
              "column": 15
            },
            "end": {
              "line": 14,
              "column": 54
            }
          },
          "id": null,
          "generator": false,
          "expression": true,
          "async": false,
          "params": [
            {
              "type": "Identifier",
              "start": 290,
              "end": 293,
              "loc": {
                "start": {
                  "line": 14,
                  "column": 16
                },
                "end": {
                  "line": 14,
                  "column": 19
                },
                "identifierName": "val"
              },
              "name": "val",
              "leadingComments": null
            }
          ],
          "body": {
            "type": "LogicalExpression",
            "start": 298,
            "end": 328,
            "loc": {
              "start": {
                "line": 14,
                "column": 24
              },
              "end": {
                "line": 14,
                "column": 54
              }
            },
            "left": {
              "type": "BinaryExpression",
              "start": 298,
              "end": 310,
              "loc": {
                "start": {
                  "line": 14,
                  "column": 24
                },
                "end": {
                  "line": 14,
                  "column": 36
                }
              },
              "left": {
                "type": "Identifier",
                "start": 298,
                "end": 301,
                "loc": {
                  "start": {
                    "line": 14,
                    "column": 24
                  },
                  "end": {
                    "line": 14,
                    "column": 27
                  },
                  "identifierName": "val"
                },
                "name": "val"
              },
              "operator": "===",
              "right": {
                "type": "BooleanLiteral",
                "start": 306,
                "end": 310,
                "loc": {
                  "start": {
                    "line": 14,
                    "column": 32
                  },
                  "end": {
                    "line": 14,
                    "column": 36
                  }
                },
                "value": true
              }
            },
            "operator": "||",
            "right": {
              "type": "BinaryExpression",
              "start": 314,
              "end": 328,
              "loc": {
                "start": {
                  "line": 14,
                  "column": 40
                },
                "end": {
                  "line": 14,
                  "column": 54
                }
              },
              "left": {
                "type": "Identifier",
                "start": 314,
                "end": 317,
                "loc": {
                  "start": {
                    "line": 14,
                    "column": 40
                  },
                  "end": {
                    "line": 14,
                    "column": 43
                  },
                  "identifierName": "val"
                },
                "name": "val"
              },
              "operator": "===",
              "right": {
                "type": "StringLiteral",
                "start": 322,
                "end": 328,
                "loc": {
                  "start": {
                    "line": 14,
                    "column": 48
                  },
                  "end": {
                    "line": 14,
                    "column": 54
                  }
                },
                "extra": {
                  "rawValue": "true",
                  "raw": "'true'"
                },
                "value": "true"
              }
            }
          },
          "leadingComments": [
            {
              "type": "CommentBlock",
              "value": "*\r\n * Returns true if `val` is true or equal to string 'true'\r\n *\r\n * @param val\r\n * @returns {boolean}\r\n *\r\n * @example\r\n *\r\n *      isTrue(true) // => true\r\n *      isTrue('true') // => true\r\n *      isTrue([true]) // => false\r\n *      isTrue('false') // => false\r\n ",
              "start": 0,
              "end": 272,
              "loc": {
                "start": {
                  "line": 1,
                  "column": 0
                },
                "end": {
                  "line": 13,
                  "column": 3
                }
              }
            }
          ],
          "trailingComments": []
        },
        "leadingComments": [
          {
            "type": "CommentBlock",
            "value": "*\r\n * Returns true if `val` is true or equal to string 'true'\r\n *\r\n * @param val\r\n * @returns {boolean}\r\n *\r\n * @example\r\n *\r\n *      isTrue(true) // => true\r\n *      isTrue('true') // => true\r\n *      isTrue([true]) // => false\r\n *      isTrue('false') // => false\r\n ",
            "start": 0,
            "end": 272,
            "loc": {
              "start": {
                "line": 1,
                "column": 0
              },
              "end": {
                "line": 13,
                "column": 3
              }
            }
          }
        ]
      }
    ],
    "directives": []
  },
  "comments": [
    {
      "type": "CommentBlock",
      "value": "*\r\n * Returns true if `val` is true or equal to string 'true'\r\n *\r\n * @param val\r\n * @returns {boolean}\r\n *\r\n * @example\r\n *\r\n *      isTrue(true) // => true\r\n *      isTrue('true') // => true\r\n *      isTrue([true]) // => false\r\n *      isTrue('false') // => false\r\n ",
      "start": 0,
      "end": 272,
      "loc": {
        "start": {
          "line": 1,
          "column": 0
        },
        "end": {
          "line": 13,
          "column": 3
        }
      }
    }
  ],
  "tokens": [
    {
      "type": "CommentBlock",
      "value": "*\r\n * Returns true if `val` is true or equal to string 'true'\r\n *\r\n * @param val\r\n * @returns {boolean}\r\n *\r\n * @example\r\n *\r\n *      isTrue(true) // => true\r\n *      isTrue('true') // => true\r\n *      isTrue([true]) // => false\r\n *      isTrue('false') // => false\r\n ",
      "start": 0,
      "end": 272,
      "loc": {
        "start": {
          "line": 1,
          "column": 0
        },
        "end": {
          "line": 13,
          "column": 3
        }
      }
    },
    {
      "type": {
        "label": "export",
        "keyword": "export",
        "beforeExpr": false,
        "startsExpr": false,
        "rightAssociative": false,
        "isLoop": false,
        "isAssign": false,
        "prefix": false,
        "postfix": false,
        "binop": null,
        "updateContext": null
      },
      "value": "export",
      "start": 274,
      "end": 280,
      "loc": {
        "start": {
          "line": 14,
          "column": 0
        },
        "end": {
          "line": 14,
          "column": 6
        }
      }
    },
    {
      "type": {
        "label": "default",
        "keyword": "default",
        "beforeExpr": true,
        "startsExpr": false,
        "rightAssociative": false,
        "isLoop": false,
        "isAssign": false,
        "prefix": false,
        "postfix": false,
        "binop": null,
        "updateContext": null
      },
      "value": "default",
      "start": 281,
      "end": 288,
      "loc": {
        "start": {
          "line": 14,
          "column": 7
        },
        "end": {
          "line": 14,
          "column": 14
        }
      }
    },
    {
      "type": {
        "label": "(",
        "beforeExpr": true,
        "startsExpr": true,
        "rightAssociative": false,
        "isLoop": false,
        "isAssign": false,
        "prefix": false,
        "postfix": false,
        "binop": null
      },
      "start": 289,
      "end": 290,
      "loc": {
        "start": {
          "line": 14,
          "column": 15
        },
        "end": {
          "line": 14,
          "column": 16
        }
      }
    },
    {
      "type": {
        "label": "name",
        "beforeExpr": false,
        "startsExpr": true,
        "rightAssociative": false,
        "isLoop": false,
        "isAssign": false,
        "prefix": false,
        "postfix": false,
        "binop": null
      },
      "value": "val",
      "start": 290,
      "end": 293,
      "loc": {
        "start": {
          "line": 14,
          "column": 16
        },
        "end": {
          "line": 14,
          "column": 19
        }
      }
    },
    {
      "type": {
        "label": ")",
        "beforeExpr": false,
        "startsExpr": false,
        "rightAssociative": false,
        "isLoop": false,
        "isAssign": false,
        "prefix": false,
        "postfix": false,
        "binop": null
      },
      "start": 293,
      "end": 294,
      "loc": {
        "start": {
          "line": 14,
          "column": 19
        },
        "end": {
          "line": 14,
          "column": 20
        }
      }
    },
    {
      "type": {
        "label": "=>",
        "beforeExpr": true,
        "startsExpr": false,
        "rightAssociative": false,
        "isLoop": false,
        "isAssign": false,
        "prefix": false,
        "postfix": false,
        "binop": null,
        "updateContext": null
      },
      "start": 295,
      "end": 297,
      "loc": {
        "start": {
          "line": 14,
          "column": 21
        },
        "end": {
          "line": 14,
          "column": 23
        }
      }
    },
    {
      "type": {
        "label": "name",
        "beforeExpr": false,
        "startsExpr": true,
        "rightAssociative": false,
        "isLoop": false,
        "isAssign": false,
        "prefix": false,
        "postfix": false,
        "binop": null
      },
      "value": "val",
      "start": 298,
      "end": 301,
      "loc": {
        "start": {
          "line": 14,
          "column": 24
        },
        "end": {
          "line": 14,
          "column": 27
        }
      }
    },
    {
      "type": {
        "label": "==/!=",
        "beforeExpr": true,
        "startsExpr": false,
        "rightAssociative": false,
        "isLoop": false,
        "isAssign": false,
        "prefix": false,
        "postfix": false,
        "binop": 6,
        "updateContext": null
      },
      "value": "===",
      "start": 302,
      "end": 305,
      "loc": {
        "start": {
          "line": 14,
          "column": 28
        },
        "end": {
          "line": 14,
          "column": 31
        }
      }
    },
    {
      "type": {
        "label": "true",
        "keyword": "true",
        "beforeExpr": false,
        "startsExpr": true,
        "rightAssociative": false,
        "isLoop": false,
        "isAssign": false,
        "prefix": false,
        "postfix": false,
        "binop": null,
        "updateContext": null
      },
      "value": "true",
      "start": 306,
      "end": 310,
      "loc": {
        "start": {
          "line": 14,
          "column": 32
        },
        "end": {
          "line": 14,
          "column": 36
        }
      }
    },
    {
      "type": {
        "label": "||",
        "beforeExpr": true,
        "startsExpr": false,
        "rightAssociative": false,
        "isLoop": false,
        "isAssign": false,
        "prefix": false,
        "postfix": false,
        "binop": 1,
        "updateContext": null
      },
      "value": "||",
      "start": 311,
      "end": 313,
      "loc": {
        "start": {
          "line": 14,
          "column": 37
        },
        "end": {
          "line": 14,
          "column": 39
        }
      }
    },
    {
      "type": {
        "label": "name",
        "beforeExpr": false,
        "startsExpr": true,
        "rightAssociative": false,
        "isLoop": false,
        "isAssign": false,
        "prefix": false,
        "postfix": false,
        "binop": null
      },
      "value": "val",
      "start": 314,
      "end": 317,
      "loc": {
        "start": {
          "line": 14,
          "column": 40
        },
        "end": {
          "line": 14,
          "column": 43
        }
      }
    },
    {
      "type": {
        "label": "==/!=",
        "beforeExpr": true,
        "startsExpr": false,
        "rightAssociative": false,
        "isLoop": false,
        "isAssign": false,
        "prefix": false,
        "postfix": false,
        "binop": 6,
        "updateContext": null
      },
      "value": "===",
      "start": 318,
      "end": 321,
      "loc": {
        "start": {
          "line": 14,
          "column": 44
        },
        "end": {
          "line": 14,
          "column": 47
        }
      }
    },
    {
      "type": {
        "label": "string",
        "beforeExpr": false,
        "startsExpr": true,
        "rightAssociative": false,
        "isLoop": false,
        "isAssign": false,
        "prefix": false,
        "postfix": false,
        "binop": null,
        "updateContext": null
      },
      "value": "true",
      "start": 322,
      "end": 328,
      "loc": {
        "start": {
          "line": 14,
          "column": 48
        },
        "end": {
          "line": 14,
          "column": 54
        }
      }
    },
    {
      "type": {
        "label": ";",
        "beforeExpr": true,
        "startsExpr": false,
        "rightAssociative": false,
        "isLoop": false,
        "isAssign": false,
        "prefix": false,
        "postfix": false,
        "binop": null,
        "updateContext": null
      },
      "start": 328,
      "end": 329,
      "loc": {
        "start": {
          "line": 14,
          "column": 54
        },
        "end": {
          "line": 14,
          "column": 55
        }
      }
    },
    {
      "type": {
        "label": "eof",
        "beforeExpr": false,
        "startsExpr": false,
        "rightAssociative": false,
        "isLoop": false,
        "isAssign": false,
        "prefix": false,
        "postfix": false,
        "binop": null,
        "updateContext": null
      },
      "start": 331,
      "end": 331,
      "loc": {
        "start": {
          "line": 15,
          "column": 0
        },
        "end": {
          "line": 15,
          "column": 0
        }
      }
    }
  ]
}